iceBlinkPico-main/projects/sine2/gtkwave/memory.sv
module memory #(
    parameter INIT_FILE = ""
)(
    input logic     clk,
    input logic     [6:0] read_address,
    output logic    [8:0] read_data
);

    logic [9:0] sample_memory [0:127];

    initial if (INIT_FILE) begin
        $readmemh(INIT_FILE, sample_memory);
    end

    always_ff @(posedge clk) begin
        read_data <= sample_memory[read_address];
    end

endmodule

iceBlinkPico-main/projects/sine2/gtkwave/sine2.sv
`include "memory.sv"

module top(
    input logic     clk, 
    output logic    _9b,    // D0
    output logic    _6a,    // D1
    output logic    _4a,    // D2
    output logic    _2a,    // D3
    output logic    _0a,    // D4
    output logic    _5a,    // D5
    output logic    _3b,    // D6
    output logic    _49a,   // D7
    output logic    _45a,   // D8
    output logic    _48b    // D9
);

    logic [8:0] counter = 0;
    logic [8:0] quarter_wave_value;
    logic [9:0] output_value;
    logic [6:0] memory_address;
    
    // Extract the quadrant (2 MSB of counter)
    logic [1:0] quadrant;
    assign quadrant = counter[8:7];
    
    memory #(
        .INIT_FILE("sine2.txt")
    ) u1 (
        .clk(clk),
        .read_address(memory_address),
        .read_data(quarter_wave_value)
    );
    
    // Increment counter on each clock edge
    always_ff @(posedge clk) begin
        counter <= counter + 1;
    end
    
    // Calculate memory address based on quadrant
    always_comb begin
        case(quadrant)
            2'b00: memory_address = counter[6:0];             // First quadrant (0-127): direct mapping
            2'b01: memory_address = 7'd127 - counter[6:0];    // Second quadrant (128-255): reverse order
            2'b10: memory_address = counter[6:0];
            2'b11: memory_address = 7'd127 - counter[6:0];
        endcase
    end
    
    // Calculate final output value based on quadrant - CORRECTED to fix orientation
    always_comb begin
        case(quadrant)
            // First half-cycle
            2'b00, 2'b01: output_value = 10'd512 + {1'b0, quarter_wave_value};
            // Second half-cycle flip back to 0
            2'b10, 2'b11: output_value = 10'd512 - {1'b0, quarter_wave_value};
        endcase
    end
    
    assign {_48b, _45a, _49a, _3b, _5a, _0a, _2a, _4a, _6a, _9b} = output_value;

endmodule

iceBlinkPico-main/projects/sine2/gtkwave/sine2_tb.sv
`timescale 10ns/10ns

module sine2_tb;

    logic clk = 0;
    logic _9b, _6a, _4a, _2a, _0a, _5a, _3b, _49a, _45a, _48b;

    logic [9:0] dac_value;
    assign dac_value = {_48b, _45a, _49a, _3b, _5a, _0a, _2a, _4a, _6a, _9b};

    top u0 (
        .clk    (clk), 
        ._9b    (_9b), 
        ._6a    (_6a), 
        ._4a    (_4a), 
        ._2a    (_2a), 
        ._0a    (_0a), 
        ._5a    (_5a), 
        ._3b    (_3b), 
        ._49a   (_49a), 
        ._45a   (_45a), 
        ._48b   (_48b)
    );

    initial begin
        $dumpfile("sine2.vcd");
        $dumpvars(0, sine2_tb);
        $dumpvars(1, dac_value);
        #10000
        $finish;
    end

    always begin
        #4
        clk = ~clk;
    end

endmodule

iceBlinkPico-main/projects/sine2/gtkwave/sine2.vcd
$date
	Mon Mar 31 18:31:27 2025
$end
$version
	Icarus Verilog
$end
$timescale
	10ns
$end
$scope module sine2_tb $end
$var wire 10 ! dac_value [9:0] $end
$var wire 1 " _9b $end
$var wire 1 # _6a $end
$var wire 1 $ _5a $end
$var wire 1 % _4a $end
$var wire 1 & _49a $end
$var wire 1 ' _48b $end
$var wire 1 ( _45a $end
$var wire 1 ) _3b $end
$var wire 1 * _2a $end
$var wire 1 + _0a $end
$var reg 1 , clk $end
$scope module u0 $end
$var wire 1 , clk $end
$var wire 9 - quarter_wave_value [8:0] $end
$var wire 2 . quadrant [1:0] $end
$var wire 1 " _9b $end
$var wire 1 # _6a $end
$var wire 1 $ _5a $end
$var wire 1 % _4a $end
$var wire 1 & _49a $end
$var wire 1 ' _48b $end
$var wire 1 ( _45a $end
$var wire 1 ) _3b $end
$var wire 1 * _2a $end
$var wire 1 + _0a $end
$var reg 9 / counter [8:0] $end
$var reg 7 0 memory_address [6:0] $end
$var reg 10 1 output_value [9:0] $end
$scope module u1 $end
$var wire 1 , clk $end
$var wire 7 2 read_address [6:0] $end
$var parameter 72 3 INIT_FILE $end
$var reg 9 4 read_data [8:0] $end
$upscope $end
$upscope $end
$upscope $end
$enddefinitions $end
$comment Show the parameter values. $end
$dumpall
b11100110110100101101110011001010011001000101110011101000111100001110100 3
$end
#0
$dumpvars
bx 4
b0 2
bx 1
b0 0
b0 /
b0 .
bx -
0,
x+
x*
x)
x(
x'
x&
x%
x$
x#
x"
bx !
$end
#4
1'
0(
0&
0)
0$
0+
0*
0%
0#
b1000000000 !
0"
b1000000000 1
b1 0
b1 2
b0 -
b0 4
b1 /
1,
#8
0,
#12
1%
b1000000110 !
1#
b10 0
b10 2
b1000000110 1
b10 /
b110 -
b110 4
1,
#16
0,
#20
1*
b1000001100 !
0#
b1000001100 1
b11 0
b11 2
b1100 -
b1100 4
b11 /
1,
#24
0,
#28
1+
0*
0%
b1000010010 !
1#
b100 0
b100 2
b1000010010 1
b100 /
b10010 -
b10010 4
1,
#32
0,
#36
1*
0#
b1000011001 !
1"
b1000011001 1
b101 0
b101 2
b11001 -
b11001 4
b101 /
1,
#40
0,
#44
1%
b1000011111 !
1#
b110 0
b110 2
b1000011111 1
b110 /
b11111 -
b11111 4
1,
#48
0,
#52
1$
0+
0*
b1000100101 !
0#
b1000100101 1
b111 0
b111 2
b100101 -
b100101 4
b111 /
1,
#56
0,
#60
1*
0%
b1000101011 !
1#
b1000 0
b1000 2
b1000101011 1
b1000 /
b101011 -
b101011 4
1,
#64
0,
#68
1+
0*
b1000110010 !
0"
b1000110010 1
b1001 0
b1001 2
b110010 -
b110010 4
b1001 /
1,
#72
0,
#76
1*
b1000111000 !
0#
b1010 0
b1010 2
b1000111000 1
b1010 /
b111000 -
b111000 4
1,
#80
0,
#84
1%
b1000111110 !
1#
b1000111110 1
b1011 0
b1011 2
b111110 -
b111110 4
b1011 /
1,
#88
0,
#92
1)
0$
0+
0*
b1001000100 !
0#
b1100 0
b1100 2
b1001000100 1
b1100 /
b1000100 -
b1000100 4
1,
#96
0,
#100
1*
0%
1#
b1001001011 !
1"
b1001001011 1
b1101 0
b1101 2
b1001011 -
b1001011 4
b1101 /
1,
#104
0,
#108
1+
0*
b1001010001 !
0#
b1110 0
b1110 2
b1001010001 1
b1110 /
b1010001 -
b1010001 4
1,
#112
0,
#116
1%
b1001010111 !
1#
b1001010111 1
b1111 0
b1111 2
b1010111 -
b1010111 4
b1111 /
1,
#120
0,
#124
1*
b1001011101 !
0#
b10000 0
b10000 2
b1001011101 1
b10000 /
b1011101 -
b1011101 4
1,
#128
0,
#132
1$
0+
0*
0%
b1001100011 !
1#
b1001100011 1
b10001 0
b10001 2
b1100011 -
b1100011 4
b10001 /
1,
#136
0,
#140
1*
b1001101001 !
0#
b10010 0
b10010 2
b1001101001 1
b10010 /
b1101001 -
b1101001 4
1,
#144
0,
#148
1+
0*
b1001110000 !
0"
b1001110000 1
b10011 0
b10011 2
b1110000 -
b1110000 4
b10011 /
1,
#152
0,
#156
1%
b1001110110 !
1#
b10100 0
b10100 2
b1001110110 1
b10100 /
b1110110 -
b1110110 4
1,
#160
0,
#164
1*
b1001111100 !
0#
b1001111100 1
b10101 0
b10101 2
b1111100 -
b1111100 4
b10101 /
1,
#168
0,
#172
1&
0)
0$
0+
0*
0%
b1010000010 !
1#
b10110 0
b10110 2
b1010000010 1
b10110 /
b10000010 -
b10000010 4
1,
#176
0,
#180
1*
b1010001000 !
0#
b1010001000 1
b10111 0
b10111 2
b10001000 -
b10001000 4
b10111 /
1,
#184
0,
#188
1%
b1010001110 !
1#
b11000 0
b11000 2
b1010001110 1
b11000 /
b10001110 -
b10001110 4
1,
#192
0,
#196
1+
0*
b1010010100 !
0#
b1010010100 1
b11001 0
b11001 2
b10010100 -
b10010100 4
b11001 /
1,
#200
0,
#204
1*
0%
b1010011010 !
1#
b11010 0
b11010 2
b1010011010 1
b11010 /
b10011010 -
b10011010 4
1,
#208
0,
#212
1$
0+
0*
b1010100000 !
0#
b1010100000 1
b11011 0
b11011 2
b10100000 -
b10100000 4
b11011 /
1,
#216
0,
#220
1%
b1010100110 !
1#
b11100 0
b11100 2
b1010100110 1
b11100 /
b10100110 -
b10100110 4
1,
#224
0,
#228
1*
b1010101100 !
0#
b1010101100 1
b11101 0
b11101 2
b10101100 -
b10101100 4
b11101 /
1,
#232
0,
#236
1+
0*
0%
b1010110010 !
1#
b11110 0
b11110 2
b1010110010 1
b11110 /
b10110010 -
b10110010 4
1,
#240
0,
#244
1*
b1010111000 !
0#
b1010111000 1
b11111 0
b11111 2
b10111000 -
b10111000 4
b11111 /
1,
#248
0,
#252
1%
b1010111101 !
1"
b100000 0
b100000 2
b1010111101 1
b100000 /
b10111101 -
b10111101 4
1,
#256
0,
#260
1)
0$
0+
0*
0%
b1011000011 !
1#
b1011000011 1
b100001 0
b100001 2
b11000011 -
b11000011 4
b100001 /
1,
#264
0,
#268
1*
b1011001001 !
0#
b100010 0
b100010 2
b1011001001 1
b100010 /
b11001001 -
b11001001 4
1,
#272
0,
#276
1%
b1011001111 !
1#
b1011001111 1
b100011 0
b100011 2
b11001111 -
b11001111 4
b100011 /
1,
#280
0,
#284
1+
0*
b1011010101 !
0#
b100100 0
b100100 2
b1011010101 1
b100100 /
b11010101 -
b11010101 4
1,
#288
0,
#292
1*
0%
1#
b1011011010 !
0"
b1011011010 1
b100101 0
b100101 2
b11011010 -
b11011010 4
b100101 /
1,
#296
0,
#300
1$
0+
0*
b1011100000 !
0#
b100110 0
b100110 2
b1011100000 1
b100110 /
b11100000 -
b11100000 4
1,
#304
0,
#308
1%
b1011100101 !
1"
b1011100101 1
b100111 0
b100111 2
b11100101 -
b11100101 4
b100111 /
1,
#312
0,
#316
1*
0%
b1011101011 !
1#
b101000 0
b101000 2
b1011101011 1
b101000 /
b11101011 -
b11101011 4
1,
#320
0,
#324
1+
0*
b1011110001 !
0#
b1011110001 1
b101001 0
b101001 2
b11110001 -
b11110001 4
b101001 /
1,
#328
0,
#332
1%
1#
b1011110110 !
0"
b101010 0
b101010 2
b1011110110 1
b101010 /
b11110110 -
b11110110 4
1,
#336
0,
#340
1*
b1011111100 !
0#
b1011111100 1
b101011 0
b101011 2
b11111100 -
b11111100 4
b101011 /
1,
#344
0,
#348
1(
0&
0)
0$
0+
0*
0%
b1100000001 !
1"
b101100 0
b101100 2
b1100000001 1
b101100 /
b100000001 -
b100000001 4
1,
#352
0,
#356
1%
1#
b1100000110 !
0"
b1100000110 1
b101101 0
b101101 2
b100000110 -
b100000110 4
b101101 /
1,
#360
0,
#364
1*
b1100001100 !
0#
b101110 0
b101110 2
b1100001100 1
b101110 /
b100001100 -
b100001100 4
1,
#368
0,
#372
1+
0*
0%
b1100010001 !
1"
b1100010001 1
b101111 0
b101111 2
b100010001 -
b100010001 4
b101111 /
1,
#376
0,
#380
1%
1#
b1100010110 !
0"
b110000 0
b110000 2
b1100010110 1
b110000 /
b100010110 -
b100010110 4
1,
#384
0,
#388
1*
b1100011100 !
0#
b1100011100 1
b110001 0
b110001 2
b100011100 -
b100011100 4
b110001 /
1,
#392
0,
#396
1$
0+
0*
0%
b1100100001 !
1"
b110010 0
b110010 2
b1100100001 1
b110010 /
b100100001 -
b100100001 4
1,
#400
0,
#404
1%
1#
b1100100110 !
0"
b1100100110 1
b110011 0
b110011 2
b100100110 -
b100100110 4
b110011 /
1,
#408
0,
#412
1*
0%
b1100101011 !
1"
b110100 0
b110100 2
b1100101011 1
b110100 /
b100101011 -
b100101011 4
1,
#416
0,
#420
1+
0*
0#
b1100110000 !
0"
b1100110000 1
b110101 0
b110101 2
b100110000 -
b100110000 4
b110101 /
1,
#424
0,
#428
1%
b1100110101 !
1"
b110110 0
b110110 2
b1100110101 1
b110110 /
b100110101 -
b100110101 4
1,
#432
0,
#436
1*
0%
1#
b1100111010 !
0"
b1100111010 1
b110111 0
b110111 2
b100111010 -
b100111010 4
b110111 /
1,
#440
0,
#444
1%
b1100111111 !
1"
b111000 0
b111000 2
b1100111111 1
b111000 /
b100111111 -
b100111111 4
1,
#448
0,
#452
1)
0$
0+
0*
0#
b1101000100 !
0"
b1101000100 1
b111001 0
b111001 2
b101000100 -
b101000100 4
b111001 /
1,
#456
0,
#460
1*
0%
b1101001001 !
1"
b111010 0
b111010 2
b1101001001 1
b111010 /
b101001001 -
b101001001 4
1,
#464
0,
#468
1%
1#
b1101001110 !
0"
b1101001110 1
b111011 0
b111011 2
b101001110 -
b101001110 4
b111011 /
1,
#472
0,
#476
1+
0*
b1101010010 !
0%
b111100 0
b111100 2
b1101010010 1
b111100 /
b101010010 -
b101010010 4
1,
#480
0,
#484
1%
b1101010111 !
1"
b1101010111 1
b111101 0
b111101 2
b101010111 -
b101010111 4
b111101 /
1,
#488
0,
#492
1*
0#
b1101011100 !
0"
b111110 0
b111110 2
b1101011100 1
b111110 /
b101011100 -
b101011100 4
1,
#496
0,
#500
1$
0+
0*
b1101100000 !
0%
b1101100000 1
b111111 0
b111111 2
b101100000 -
b101100000 4
b111111 /
1,
#504
0,
#508
1%
b1101100101 !
1"
b1000000 0
b1000000 2
b1101100101 1
b1000000 /
b101100101 -
b101100101 4
1,
#512
0,
#516
1*
b1101101001 !
0%
b1101101001 1
b1000001 0
b1000001 2
b101101001 -
b101101001 4
b1000001 /
1,
#520
0,
#524
1%
1#
b1101101110 !
0"
b1000010 0
b1000010 2
b1101101110 1
b1000010 /
b101101110 -
b101101110 4
1,
#528
0,
#532
1+
0*
b1101110010 !
0%
b1101110010 1
b1000011 0
b1000011 2
b101110010 -
b101110010 4
b1000011 /
1,
#536
0,
#540
b1101110110 !
1%
b1000100 0
b1000100 2
b1101110110 1
b1000100 /
b101110110 -
b101110110 4
1,
#544
0,
#548
1*
b1101111010 !
0%
b1101111010 1
b1000101 0
b1000101 2
b101111010 -
b101111010 4
b1000101 /
1,
#552
0,
#556
1%
b1101111111 !
1"
b1000110 0
b1000110 2
b1101111111 1
b1000110 /
b101111111 -
b101111111 4
1,
#560
0,
#564
1&
0)
0$
0+
0*
b1110000011 !
0%
b1110000011 1
b1000111 0
b1000111 2
b110000011 -
b110000011 4
b1000111 /
1,
#568
0,
#572
b1110000111 !
1%
b1001000 0
b1001000 2
b1110000111 1
b1001000 /
b110000111 -
b110000111 4
1,
#576
0,
#580
1*
b1110001011 !
0%
b1110001011 1
b1001001 0
b1001001 2
b110001011 -
b110001011 4
b1001001 /
1,
#584
0,
#588
b1110001111 !
1%
b1001010 0
b1001010 2
b1110001111 1
b1001010 /
b110001111 -
b110001111 4
1,
#592
0,
#596
1+
0*
b1110010011 !
0%
b1110010011 1
b1001011 0
b1001011 2
b110010011 -
b110010011 4
b1001011 /
1,
#600
0,
#604
b1110010111 !
1%
b1001100 0
b1001100 2
b1110010111 1
b1001100 /
b110010111 -
b110010111 4
1,
#608
0,
#612
1*
0%
b1110011010 !
0"
b1110011010 1
b1001101 0
b1001101 2
b110011010 -
b110011010 4
b1001101 /
1,
#616
0,
#620
b1110011110 !
1%
b1001110 0
b1001110 2
b1110011110 1
b1001110 /
b110011110 -
b110011110 4
1,
#624
0,
#628
1$
0+
0*
b1110100010 !
0%
b1110100010 1
b1001111 0
b1001111 2
b110100010 -
b110100010 4
b1001111 /
1,
#632
0,
#636
1%
0#
b1110100101 !
1"
b1010000 0
b1010000 2
b1110100101 1
b1010000 /
b110100101 -
b110100101 4
1,
#640
0,
#644
1*
b1110101001 !
0%
b1110101001 1
b1010001 0
b1010001 2
b110101001 -
b110101001 4
b1010001 /
1,
#648
0,
#652
1%
b1110101100 !
0"
b1010010 0
b1010010 2
b1110101100 1
b1010010 /
b110101100 -
b110101100 4
1,
#656
0,
#660
1+
0*
b1110110000 !
0%
b1110110000 1
b1010011 0
b1010011 2
b110110000 -
b110110000 4
b1010011 /
1,
#664
0,
#668
1#
b1110110011 !
1"
b1010100 0
b1010100 2
b1110110011 1
b1010100 /
b110110011 -
b110110011 4
1,
#672
0,
#676
1%
b1110110110 !
0"
b1110110110 1
b1010101 0
b1010101 2
b110110110 -
b110110110 4
b1010101 /
1,
#680
0,
#684
1*
0%
0#
b1110111001 !
1"
b1010110 0
b1010110 2
b1110111001 1
b1010110 /
b110111001 -
b110111001 4
1,
#688
0,
#692
b1110111101 !
1%
b1110111101 1
b1010111 0
b1010111 2
b110111101 -
b110111101 4
b1010111 /
1,
#696
0,
#700
1)
0$
0+
0*
0%
b1111000000 !
0"
b1011000 0
b1011000 2
b1111000000 1
b1011000 /
b111000000 -
b111000000 4
1,
#704
0,
#708
1#
b1111000011 !
1"
b1111000011 1
b1011001 0
b1011001 2
b111000011 -
b111000011 4
b1011001 /
1,
#712
0,
#716
1%
b1111000110 !
0"
b1011010 0
b1011010 2
b1111000110 1
b1011010 /
b111000110 -
b111000110 4
1,
#720
0,
#724
1*
0%
b1111001000 !
0#
b1111001000 1
b1011011 0
b1011011 2
b111001000 -
b111001000 4
b1011011 /
1,
#728
0,
#732
1#
b1111001011 !
1"
b1011100 0
b1011100 2
b1111001011 1
b1011100 /
b111001011 -
b111001011 4
1,
#736
0,
#740
1%
b1111001110 !
0"
b1111001110 1
b1011101 0
b1011101 2
b111001110 -
b111001110 4
b1011101 /
1,
#744
0,
#748
1+
0*
0%
0#
b1111010001 !
1"
b1011110 0
b1011110 2
b1111010001 1
b1011110 /
b111010001 -
b111010001 4
1,
#752
0,
#756
b1111010011 !
1#
b1111010011 1
b1011111 0
b1011111 2
b111010011 -
b111010011 4
b1011111 /
1,
#760
0,
#764
1%
b1111010110 !
0"
b1100000 0
b1100000 2
b1111010110 1
b1100000 /
b111010110 -
b111010110 4
1,
#768
0,
#772
1*
0%
b1111011000 !
0#
b1111011000 1
b1100001 0
b1100001 2
b111011000 -
b111011000 4
b1100001 /
1,
#776
0,
#780
b1111011010 !
1#
b1100010 0
b1100010 2
b1111011010 1
b1100010 /
b111011010 -
b111011010 4
1,
#784
0,
#788
1%
0#
b1111011101 !
1"
b1111011101 1
b1100011 0
b1100011 2
b111011101 -
b111011101 4
b1100011 /
1,
#792
0,
#796
b1111011111 !
1#
b1100100 0
b1100100 2
b1111011111 1
b1100100 /
b111011111 -
b111011111 4
1,
#800
0,
#804
1$
0+
0*
0%
b1111100001 !
0#
b1111100001 1
b1100101 0
b1100101 2
b111100001 -
b111100001 4
b1100101 /
1,
#808
0,
#812
b1111100011 !
1#
b1100110 0
b1100110 2
b1111100011 1
b1100110 /
b111100011 -
b111100011 4
1,
#816
0,
#820
1%
b1111100101 !
0#
b1111100101 1
b1100111 0
b1100111 2
b111100101 -
b111100101 4
b1100111 /
1,
#824
0,
#828
b1111100111 !
1#
b1101000 0
b1101000 2
b1111100111 1
b1101000 /
b111100111 -
b111100111 4
1,
#832
0,
#836
1*
0%
b1111101001 !
0#
b1111101001 1
b1101001 0
b1101001 2
b111101001 -
b111101001 4
b1101001 /
1,
#840
0,
#844
b1111101011 !
1#
b1101010 0
b1101010 2
b1111101011 1
b1101010 /
b111101011 -
b111101011 4
1,
#848
0,
#852
1%
0#
b1111101100 !
0"
b1111101100 1
b1101011 0
b1101011 2
b111101100 -
b111101100 4
b1101011 /
1,
#856
0,
#860
b1111101110 !
1#
b1101100 0
b1101100 2
b1111101110 1
b1101100 /
b111101110 -
b111101110 4
1,
#864
0,
#868
1+
0*
0%
b1111110000 !
0#
b1111110000 1
b1101101 0
b1101101 2
b111110000 -
b111110000 4
b1101101 /
1,
#872
0,
#876
b1111110001 !
1"
b1101110 0
b1101110 2
b1111110001 1
b1101110 /
b111110001 -
b111110001 4
1,
#880
0,
#884
b1111110011 !
1#
b1111110011 1
b1101111 0
b1101111 2
b111110011 -
b111110011 4
b1101111 /
1,
#888
0,
#892
1%
0#
b1111110100 !
0"
b1110000 0
b1110000 2
b1111110100 1
b1110000 /
b111110100 -
b111110100 4
1,
#896
0,
#900
b1111110101 !
1"
b1111110101 1
b1110001 0
b1110001 2
b111110101 -
b111110101 4
b1110001 /
1,
#904
0,
#908
1#
b1111110110 !
0"
b1110010 0
b1110010 2
b1111110110 1
b1110010 /
b111110110 -
b111110110 4
1,
#912
0,
#916
b1111110111 !
1"
b1111110111 1
b1110011 0
b1110011 2
b111110111 -
b111110111 4
b1110011 /
1,
#920
0,
#924
1*
0%
b1111111001 !
0#
b1110100 0
b1110100 2
b1111111001 1
b1110100 /
b111111001 -
b111111001 4
1,
#928
0,
#932
b1110101 0
b1110101 2
b1110101 /
1,
#936
0,
#940
1#
b1111111010 !
0"
b1110110 0
b1110110 2
b1111111010 1
b1110110 /
b111111010 -
b111111010 4
1,
#944
0,
#948
b1111111011 !
1"
b1111111011 1
b1110111 0
b1110111 2
b111111011 -
b111111011 4
b1110111 /
1,
#952
0,
#956
1%
0#
b1111111100 !
0"
b1111000 0
b1111000 2
b1111111100 1
b1111000 /
b111111100 -
b111111100 4
1,
#960
0,
#964
b1111111101 !
1"
b1111111101 1
b1111001 0
b1111001 2
b111111101 -
b111111101 4
b1111001 /
1,
#968
0,
#972
b1111010 0
b1111010 2
b1111010 /
1,
#976
0,
#980
1#
b1111111110 !
0"
b1111111110 1
b1111011 0
b1111011 2
b111111110 -
b111111110 4
b1111011 /
1,
#984
0,
#988
b1111100 0
b1111100 2
b1111100 /
1,
#992
0,
#996
b1111101 0
b1111101 2
b1111101 /
1,
#1000
0,
#1004
b1111111111 !
1"
b1111110 0
b1111110 2
b1111111111 1
b1111110 /
b111111111 -
b111111111 4
1,
#1008
0,
#1012
b1111111 0
b1111111 2
b1111111 /
1,
#1016
0,
#1020
b1 .
b10000000 /
1,
#1024
0,
#1028
b1111110 0
b1111110 2
b10000001 /
1,
#1032
0,
#1036
b1111101 0
b1111101 2
b10000010 /
1,
#1040
0,
#1044
b1111100 0
b1111100 2
b10000011 /
1,
#1048
0,
#1052
b1111111110 !
0"
b1111011 0
b1111011 2
b1111111110 1
b10000100 /
b111111110 -
b111111110 4
1,
#1056
0,
#1060
b1111010 0
b1111010 2
b10000101 /
1,
#1064
0,
#1068
b1111001 0
b1111001 2
b10000110 /
1,
#1072
0,
#1076
0#
b1111111101 !
1"
b1111111101 1
b1111000 0
b1111000 2
b111111101 -
b111111101 4
b10000111 /
1,
#1080
0,
#1084
b1110111 0
b1110111 2
b10001000 /
1,
#1088
0,
#1092
b1111111100 !
0"
b1111111100 1
b1110110 0
b1110110 2
b111111100 -
b111111100 4
b10001001 /
1,
#1096
0,
#1100
0%
1#
b1111111011 !
1"
b1110101 0
b1110101 2
b1111111011 1
b10001010 /
b111111011 -
b111111011 4
1,
#1104
0,
#1108
b1111111010 !
0"
b1111111010 1
b1110100 0
b1110100 2
b111111010 -
b111111010 4
b10001011 /
1,
#1112
0,
#1116
0#
b1111111001 !
1"
b1110011 0
b1110011 2
b1111111001 1
b10001100 /
b111111001 -
b111111001 4
1,
#1120
0,
#1124
b1110010 0
b1110010 2
b10001101 /
1,
#1128
0,
#1132
0*
1%
b1111110111 !
1#
b1110001 0
b1110001 2
b1111110111 1
b10001110 /
b111110111 -
b111110111 4
1,
#1136
0,
#1140
b1111110110 !
0"
b1111110110 1
b1110000 0
b1110000 2
b111110110 -
b111110110 4
b10001111 /
1,
#1144
0,
#1148
0#
b1111110101 !
1"
b1101111 0
b1101111 2
b1111110101 1
b10010000 /
b111110101 -
b111110101 4
1,
#1152
0,
#1156
b1111110100 !
0"
b1111110100 1
b1101110 0
b1101110 2
b111110100 -
b111110100 4
b10010001 /
1,
#1160
0,
#1164
0%
1#
b1111110011 !
1"
b1101101 0
b1101101 2
b1111110011 1
b10010010 /
b111110011 -
b111110011 4
1,
#1168
0,
#1172
b1111110001 !
0#
b1111110001 1
b1101100 0
b1101100 2
b111110001 -
b111110001 4
b10010011 /
1,
#1176
0,
#1180
b1111110000 !
0"
b1101011 0
b1101011 2
b1111110000 1
b10010100 /
b111110000 -
b111110000 4
1,
#1184
0,
#1188
0+
1*
1%
b1111101110 !
1#
b1111101110 1
b1101010 0
b1101010 2
b111101110 -
b111101110 4
b10010101 /
1,
#1192
0,
#1196
b1111101100 !
0#
b1101001 0
b1101001 2
b1111101100 1
b10010110 /
b111101100 -
b111101100 4
1,
#1200
0,
#1204
0%
1#
b1111101011 !
1"
b1111101011 1
b1101000 0
b1101000 2
b111101011 -
b111101011 4
b10010111 /
1,
#1208
0,
#1212
b1111101001 !
0#
b1100111 0
b1100111 2
b1111101001 1
b10011000 /
b111101001 -
b111101001 4
1,
#1216
0,
#1220
0*
1%
b1111100111 !
1#
b1111100111 1
b1100110 0
b1100110 2
b111100111 -
b111100111 4
b10011001 /
1,
#1224
0,
#1228
b1111100101 !
0#
b1100101 0
b1100101 2
b1111100101 1
b10011010 /
b111100101 -
b111100101 4
1,
#1232
0,
#1236
0%
b1111100011 !
1#
b1111100011 1
b1100100 0
b1100100 2
b111100011 -
b111100011 4
b10011011 /
1,
#1240
0,
#1244
b1111100001 !
0#
b1100011 0
b1100011 2
b1111100001 1
b10011100 /
b111100001 -
b111100001 4
1,
#1248
0,
#1252
0$
1+
1*
1%
b1111011111 !
1#
b1111011111 1
b1100010 0
b1100010 2
b111011111 -
b111011111 4
b10011101 /
1,
#1256
0,
#1260
b1111011101 !
0#
b1100001 0
b1100001 2
b1111011101 1
b10011110 /
b111011101 -
b111011101 4
1,
#1264
0,
#1268
0%
1#
b1111011010 !
0"
b1111011010 1
b1100000 0
b1100000 2
b111011010 -
b111011010 4
b10011111 /
1,
#1272
0,
#1276
b1111011000 !
0#
b1011111 0
b1011111 2
b1111011000 1
b10100000 /
b111011000 -
b111011000 4
1,
#1280
0,
#1284
0*
1%
b1111010110 !
1#
b1111010110 1
b1011110 0
b1011110 2
b111010110 -
b111010110 4
b10100001 /
1,
#1288
0,
#1292
0%
b1111010011 !
1"
b1011101 0
b1011101 2
b1111010011 1
b10100010 /
b111010011 -
b111010011 4
1,
#1296
0,
#1300
b1111010001 !
0#
b1111010001 1
b1011100 0
b1011100 2
b111010001 -
b111010001 4
b10100011 /
1,
#1304
0,
#1308
0+
1*
1%
1#
b1111001110 !
0"
b1011011 0
b1011011 2
b1111001110 1
b10100100 /
b111001110 -
b111001110 4
1,
#1312
0,
#1316
0%
b1111001011 !
1"
b1111001011 1
b1011010 0
b1011010 2
b111001011 -
b111001011 4
b10100101 /
1,
#1320
0,
#1324
0#
b1111001000 !
0"
b1011001 0
b1011001 2
b1111001000 1
b10100110 /
b111001000 -
b111001000 4
1,
#1328
0,
#1332
0*
1%
b1111000110 !
1#
b1111000110 1
b1011000 0
b1011000 2
b111000110 -
b111000110 4
b10100111 /
1,
#1336
0,
#1340
0%
b1111000011 !
1"
b1010111 0
b1010111 2
b1111000011 1
b10101000 /
b111000011 -
b111000011 4
1,
#1344
0,
#1348
0#
b1111000000 !
0"
b1111000000 1
b1010110 0
b1010110 2
b111000000 -
b111000000 4
b10101001 /
1,
#1352
0,
#1356
0)
1$
1+
1*
1%
b1110111101 !
1"
b1010101 0
b1010101 2
b1110111101 1
b10101010 /
b110111101 -
b110111101 4
1,
#1360
0,
#1364
b1110111001 !
0%
b1110111001 1
b1010100 0
b1010100 2
b110111001 -
b110111001 4
b10101011 /
1,
#1368
0,
#1372
0*
1%
1#
b1110110110 !
0"
b1010011 0
b1010011 2
b1110110110 1
b10101100 /
b110110110 -
b110110110 4
1,
#1376
0,
#1380
0%
b1110110011 !
1"
b1110110011 1
b1010010 0
b1010010 2
b110110011 -
b110110011 4
b10101101 /
1,
#1384
0,
#1388
0#
b1110110000 !
0"
b1010001 0
b1010001 2
b1110110000 1
b10101110 /
b110110000 -
b110110000 4
1,
#1392
0,
#1396
0+
1*
b1110101100 !
1%
b1110101100 1
b1010000 0
b1010000 2
b110101100 -
b110101100 4
b10101111 /
1,
#1400
0,
#1404
0%
b1110101001 !
1"
b1001111 0
b1001111 2
b1110101001 1
b10110000 /
b110101001 -
b110101001 4
1,
#1408
0,
#1412
0*
b1110100101 !
1%
b1110100101 1
b1001110 0
b1001110 2
b110100101 -
b110100101 4
b10110001 /
1,
#1416
0,
#1420
0%
1#
b1110100010 !
0"
b1001101 0
b1001101 2
b1110100010 1
b10110010 /
b110100010 -
b110100010 4
1,
#1424
0,
#1428
0$
1+
1*
b1110011110 !
1%
b1110011110 1
b1001100 0
b1001100 2
b110011110 -
b110011110 4
b10110011 /
1,
#1432
0,
#1436
b1110011010 !
0%
b1001011 0
b1001011 2
b1110011010 1
b10110100 /
b110011010 -
b110011010 4
1,
#1440
0,
#1444
0*
1%
b1110010111 !
1"
b1110010111 1
b1001010 0
b1001010 2
b110010111 -
b110010111 4
b10110101 /
1,
#1448
0,
#1452
b1110010011 !
0%
b1001001 0
b1001001 2
b1110010011 1
b10110110 /
b110010011 -
b110010011 4
1,
#1456
0,
#1460
0+
1*
b1110001111 !
1%
b1110001111 1
b1001000 0
b1001000 2
b110001111 -
b110001111 4
b10110111 /
1,
#1464
0,
#1468
b1110001011 !
0%
b1000111 0
b1000111 2
b1110001011 1
b10111000 /
b110001011 -
b110001011 4
1,
#1472
0,
#1476
0*
b1110000111 !
1%
b1110000111 1
b1000110 0
b1000110 2
b110000111 -
b110000111 4
b10111001 /
1,
#1480
0,
#1484
b1110000011 !
0%
b1000101 0
b1000101 2
b1110000011 1
b10111010 /
b110000011 -
b110000011 4
1,
#1488
0,
#1492
0&
1)
1$
1+
1*
b1101111111 !
1%
b1101111111 1
b1000100 0
b1000100 2
b101111111 -
b101111111 4
b10111011 /
1,
#1496
0,
#1500
0%
b1101111010 !
0"
b1000011 0
b1000011 2
b1101111010 1
b10111100 /
b101111010 -
b101111010 4
1,
#1504
0,
#1508
0*
b1101110110 !
1%
b1101110110 1
b1000010 0
b1000010 2
b101110110 -
b101110110 4
b10111101 /
1,
#1512
0,
