iceBlinkPico-main/projects/cachef/caches/direct_mapped_cache.sv
// direct_mapped_cache.sv

module direct_mapped_cache #(
    parameter CACHE_SIZE = 256, // Total cache size in bytes
    parameter BLOCK_SIZE = 16,   // Cache block size in bytes
    parameter ASSOC = 1          // Associativity (1 for direct-mapped)
)(
    input logic clk,
    input logic reset,
    input logic [31:0] addr,
    input logic [7:0] wr_data,
    input logic wr_en,
    output logic [7:0] rd_data,
    output logic hit,
    output logic miss
);

    localparam NUM_SETS = CACHE_SIZE / (BLOCK_SIZE * ASSOC);
    localparam BLOCK_OFFSET_WIDTH = $clog2(BLOCK_SIZE);
    localparam INDEX_WIDTH = $clog2(NUM_SETS);
    localparam TAG_WIDTH = 32 - INDEX_WIDTH - BLOCK_OFFSET_WIDTH;

    logic [7:0] cache_data [NUM_SETS-1:0][BLOCK_SIZE-1:0];
    logic [TAG_WIDTH-1:0] cache_tag [NUM_SETS-1:0];
    logic valid [NUM_SETS-1:0];

    logic [TAG_WIDTH-1:0] tag;
    logic [INDEX_WIDTH-1:0] index;
    logic [BLOCK_OFFSET_WIDTH-1:0] block_offset;

    always_comb begin
        tag = addr[31 : 32 - TAG_WIDTH];
        index = addr[32 - TAG_WIDTH - 1 : BLOCK_OFFSET_WIDTH];
        block_offset = addr[BLOCK_OFFSET_WIDTH-1 : 0];
    end

    logic current_hit;
    logic current_miss;
    logic [7:0] current_rd_data;

    always_comb begin
        current_hit = (valid[index] && (cache_tag[index] == tag));
        current_miss = ~current_hit;

        if (current_hit && !wr_en) 
            current_rd_data = cache_data[index][block_offset];
        else 
            current_rd_data = 8'b0; // Default data on miss/write
    end

    always_ff @(posedge clk or posedge reset) begin
        if (reset) begin
            for (int i = 0; i < NUM_SETS; i++) 
                valid[i] <= 0;

            hit <= 0;
            miss <= 0;
            rd_data <= 8'b0;
        end else begin
            hit <= current_hit;
            miss <= current_miss;
            rd_data <= current_rd_data;

            if (current_miss || wr_en) begin
                valid[index] <= 1;
                cache_tag[index] <= tag;

                if (wr_en) 
                    cache_data[index][block_offset] <= wr_data;
            end
        end
    end

endmodule

iceBlinkPico-main/projects/cachef/testbenches/direct_mapped_cache_tb.sv
// direct_mapped_cache_tb.sv

module direct_mapped_cache_tb;

    parameter CACHE_SIZE = 256;
    parameter BLOCK_SIZE = 16; // Block size set for tests
    parameter ASSOC = 1; // Direct-mapped

    localparam PERIOD = 10; // Clock period in ns
    localparam NUM_SETS = CACHE_SIZE / (BLOCK_SIZE * ASSOC);
    localparam BLOCK_OFFSET_WIDTH = $clog2(BLOCK_SIZE);
    localparam INDEX_WIDTH = $clog2(NUM_SETS);
    localparam TAG_WIDTH = 32 - INDEX_WIDTH - BLOCK_OFFSET_WIDTH;

    logic clk;
    logic reset;
    logic [31:0] addr;
    logic [7:0] wr_data;
    logic wr_en;
    logic [7:0] rd_data;
    logic hit;
    logic miss;

     // Initial block to display parameters
    initial begin
        $display("Simulation Parameters:");
        $display("CACHE_SIZE = %0d", CACHE_SIZE);
        $display("BLOCK_SIZE = %0d", BLOCK_SIZE);
        $display("ASSOC = %0d", ASSOC);
        $display("NUM_SETS = %0d", NUM_SETS);
        $display("BLOCK_OFFSET_WIDTH = %0d", BLOCK_OFFSET_WIDTH);
        $display("INDEX_WIDTH = %0d", INDEX_WIDTH);
        $display("TAG_WIDTH = %0d", TAG_WIDTH);
    end

    // Instantiate the Cache Module
    direct_mapped_cache #(
        .CACHE_SIZE(CACHE_SIZE),
        .BLOCK_SIZE(BLOCK_SIZE),
        .ASSOC(ASSOC)
    ) dut (
        .clk(clk),
        .reset(reset),
        .addr(addr),
        .wr_data(wr_data),
        .wr_en(wr_en),
        .rd_data(rd_data),
        .hit(hit),
        .miss(miss)
    );

    // Clock Generation
    initial begin
        clk = 0;
        forever #(PERIOD/2) clk = ~clk;
    end

    // Metrics Counters
    integer total_accesses = 0;
    integer read_hits = 0;
    integer read_misses = 0;
    integer write_hits = 0;
    integer write_misses = 0;

    // Temporary counters for each test
    integer test_read_hits;
    integer test_read_misses;
    integer test_write_hits;
    integer test_write_misses;

    // Read operation task
    task read_access(input [31:0] read_addr);
        begin
            addr = read_addr;
            wr_en = 0;
            total_accesses++;
            #(PERIOD);
            if (hit) begin
                test_read_hits++;
                read_hits++;
            end else begin
                test_read_misses++;
                read_misses++;
            end
            #(PERIOD);
        end
    endtask

    // Write operation task
    task write_access(input [31:0] write_addr, input [7:0] data_to_write);
        begin
            addr = write_addr;
            wr_data = data_to_write;
            wr_en = 1;
            total_accesses++;
            #(PERIOD);
            if (miss) begin
                test_write_misses++;
                write_misses++;
            end else begin
                test_write_hits++;
                write_hits++;
            end
            #(PERIOD);
        end
    endtask

    // Function to display test results
    task display_test_results();
        $display("Test Results: Read Hits: %0d, Read Misses: %0d, Write Hits: %0d, Write Misses: %0d", 
            test_read_hits, test_read_misses, test_write_hits, test_write_misses);
        
        // Reset temporary counters for the next test
        test_read_hits = 0;
        test_read_misses = 0;
        test_write_hits = 0;
        test_write_misses = 0;
    endtask

    initial begin
        // Reset the cache
        $display("--- Resetting Cache ---");
        reset = 1;
        wr_en = 0;
        addr = 32'b0;
        wr_data = 8'b0;
        #(PERIOD * 5); // Hold reset
        reset = 0;
        #(PERIOD);

        // Initialize temporary counters
        test_read_hits = 0;
        test_read_misses = 0;
        test_write_hits = 0;
        test_write_misses = 0;

        // Basic Test Cases
        $display("--- Basic Test 1: Initial Write ---");
        write_access(32'h0000_1000, 8'hAA);
        
        $display("--- Basic Test 2: Read After Write ---");
        read_access(32'h0000_1000);
        display_test_results(); // Display totals after the test

        $display("--- Basic Test 3: Conflict Write ---");
        write_access(32'h0000_2000, 8'hBB);
        
        $display("--- Basic Test 4: Read Original Address After Conflict ---");
        read_access(32'h0000_1000);
        display_test_results(); // Display totals after the test
        
        $display("--- Basic Test 5: Read Conflict Address ---");
        read_access(32'h0000_2000);
        display_test_results(); // Display totals after the test
        
        $display("--- Basic Test 6: Write to a Different Set ---");
        write_access(32'h0000_3000, 8'hCC);
        
        $display("--- Basic Test 7: Read from New Set ---");
        read_access(32'h0000_3000);
        display_test_results(); // Display totals after the test

        // Test Cases
        $display("--- Test 8: Sequential Read Access ---");
        for (int i = 0; i < NUM_SETS * BLOCK_SIZE * 2; i = i + BLOCK_SIZE) begin 
            read_access(32'h0001_0000 + i);
        end
        display_test_results(); // Display totals after the test

        $display("--- Test 9: Strided Read Access (Stride = Block Size) ---");
        for (int i = 0; i < NUM_SETS * BLOCK_SIZE; i = i + BLOCK_SIZE) begin
            read_access(32'h0002_0000 + i);
        end
        display_test_results(); // Display totals after the test

        $display("--- Test 10: Strided Read Access (Stride < Block Size) ---");
        for (int i = 0; i < NUM_SETS * BLOCK_SIZE; i = i + (BLOCK_SIZE / 4)) begin 
            read_access(32'h0003_0000 + i);
        end
        display_test_results(); // Display totals after the test

        $display("--- Test 11: Sequential Write Access ---");
        for (int i = 0; i < NUM_SETS * BLOCK_SIZE; i = i + BLOCK_SIZE) begin
            write_access(32'h0004_0000 + i, 8'hEE);
        end
        display_test_results(); // Display totals after the test

        $display("--- Test 12: Read Back Sequential Writes ---");
        for (int i = 0; i < NUM_SETS * BLOCK_SIZE; i = i + BLOCK_SIZE) begin
            read_access(32'h0004_0000 + i);
        end
        display_test_results(); // Display totals after the test

        $display("--- Test 13: Accesses within the same set, different offsets ---");
        for (int i = 0; i < BLOCK_SIZE; i++) begin
            write_access(32'h0005_0000 + i, 8'hF0 + i); // Write different data
        end
        for (int i = 0; i < BLOCK_SIZE; i++) begin
            read_access(32'h0005_0000 + i); // Read back
        end
        display_test_results(); // Display totals after the test

        $display("--- Test 14: Random Access ---");
        read_access(32'h0006_1234);
        write_access(32'h0007_5678, 8'h11);
        read_access(32'h0008_9ABC);
        read_access(32'h0007_5678);
        display_test_results(); // Display totals after the test

        // Final Metrics
        $display("--- Simulation Complete ---");
        $display("Total Accesses: %0d", total_accesses);
        $display("Total Read Hits: %0d", read_hits);
        $display("Total Read Misses: %0d", read_misses);
        $display("Total Write Hits: %0d", write_hits);
        $display("Total Write Misses: %0d", write_misses);

        $finish; // End simulation
    end

    // Waveform dumping
    initial begin
        $dumpfile("direct_mapped_cache.vcd");
        $dumpvars(0, direct_mapped_cache_tb);
    end

endmodule

iceBlinkPico-main/projects/cachef/direct_mapped_cache.vcd
$date
	Wed May  7 13:46:50 2025
$end
$version
	Icarus Verilog
$end
$timescale
	1s
$end
$scope module direct_mapped_cache_tb $end
$var wire 8 ! rd_data [7:0] $end
$var wire 1 " miss $end
$var wire 1 # hit $end
$var parameter 32 $ ASSOC $end
$var parameter 32 % BLOCK_OFFSET_WIDTH $end
$var parameter 32 & BLOCK_SIZE $end
$var parameter 32 ' CACHE_SIZE $end
$var parameter 32 ( INDEX_WIDTH $end
$var parameter 64 ) NUM_SETS $end
$var parameter 32 * PERIOD $end
$var parameter 34 + TAG_WIDTH $end
$var reg 32 , addr [31:0] $end
$var reg 1 - clk $end
$var reg 1 . reset $end
$var reg 8 / wr_data [7:0] $end
$var reg 1 0 wr_en $end
$var integer 32 1 read_hits [31:0] $end
$var integer 32 2 read_misses [31:0] $end
$var integer 32 3 test_read_hits [31:0] $end
$var integer 32 4 test_read_misses [31:0] $end
$var integer 32 5 test_write_hits [31:0] $end
$var integer 32 6 test_write_misses [31:0] $end
$var integer 32 7 total_accesses [31:0] $end
$var integer 32 8 write_hits [31:0] $end
$var integer 32 9 write_misses [31:0] $end
$scope module dut $end
$var wire 32 : addr [31:0] $end
$var wire 1 - clk $end
$var wire 1 . reset $end
$var wire 8 ; wr_data [7:0] $end
$var wire 1 0 wr_en $end
$var parameter 32 < ASSOC $end
$var parameter 32 = BLOCK_OFFSET_WIDTH $end
$var parameter 32 > BLOCK_SIZE $end
$var parameter 32 ? CACHE_SIZE $end
$var parameter 32 @ INDEX_WIDTH $end
$var parameter 64 A NUM_SETS $end
$var parameter 34 B TAG_WIDTH $end
$var reg 5 C block_offset [4:0] $end
$var reg 1 D current_hit $end
$var reg 1 E current_miss $end
$var reg 8 F current_rd_data [7:0] $end
$var reg 1 # hit $end
$var reg 4 G index [3:0] $end
$var reg 1 " miss $end
$var reg 8 H rd_data [7:0] $end
$var reg 23 I tag [22:0] $end
$scope begin $ivl_for_loop0 $end
$var integer 32 J i [31:0] $end
$upscope $end
$upscope $end
$scope begin $ivl_for_loop1 $end
$var integer 32 K i [31:0] $end
$upscope $end
$scope begin $ivl_for_loop2 $end
$var integer 32 L i [31:0] $end
$upscope $end
$scope begin $ivl_for_loop3 $end
$var integer 32 M i [31:0] $end
$upscope $end
$scope begin $ivl_for_loop4 $end
$var integer 32 N i [31:0] $end
$upscope $end
$scope begin $ivl_for_loop5 $end
$var integer 32 O i [31:0] $end
$upscope $end
$scope begin $ivl_for_loop6 $end
$var integer 32 P i [31:0] $end
$upscope $end
$scope begin $ivl_for_loop7 $end
$var integer 32 Q i [31:0] $end
$upscope $end
$scope task display_test_results $end
$upscope $end
$scope task read_access $end
$var reg 32 R read_addr [31:0] $end
$upscope $end
$scope task write_access $end
$var reg 8 S data_to_write [7:0] $end
$var reg 32 T write_addr [31:0] $end
$upscope $end
$upscope $end
$enddefinitions $end
$comment Show the parameter values. $end
$dumpall
b10111 B
b10000 A
b100 @
b1000000000 ?
b100000 >
b101 =
b1 <
b10111 +
b1010 *
b10000 )
b100 (
b1000000000 '
b100000 &
b101 %
b1 $
$end
#0
$dumpvars
bx T
bx S
bx R
b0 Q
b0 P
b0 O
b0 N
b0 M
b0 L
b0 K
b10000 J
b0 I
b0 H
b0 G
b0 F
1E
0D
b0 C
b0 ;
b0 :
b0 9
b0 8
b0 7
bx 6
bx 5
bx 4
bx 3
b0 2
b0 1
00
b0 /
1.
0-
b0 ,
0#
0"
b0 !
$end
#5
b10000 J
1-
#10
0-
#15
b10000 J
1-
#20
0-
#25
b10000 J
1-
#30
0-
#35
b10000 J
1-
#40
0-
#45
b10000 J
1-
#50
0-
0.
#55
bx F
0E
1D
1"
1-
#60
b0 F
1E
0D
b1000 I
0-
b1 7
10
b10101010 /
b10101010 ;
b1000000000000 ,
b1000000000000 :
b10101010 S
b1000000000000 T
b0 6
b0 5
b0 4
b0 3
#65
0E
1D
1-
#70
0-
b1 9
b1 6
#75
0"
1#
1-
#80
b10101010 F
0-
b10 7
00
b1000000000000 R
#85
b10101010 !
b10101010 H
1-
#90
0-
b1 1
b1 3
#95
1-
#100
b0 F
1E
0D
b10000 I
0-
b11 7
10
b10111011 /
b10111011 ;
b10000000000000 ,
b10000000000000 :
b10111011 S
b10000000000000 T
b0 6
b0 3
#105
0E
1D
b0 !
b0 H
1"
0#
1-
#110
0-
b10 9
b1 6
#115
0"
1#
1-
#120
1E
0D
b1000 I
0-
b100 7
00
b1000000000000 ,
b1000000000000 :
#125
b10111011 F
0E
1D
1"
0#
1-
#130
0-
b1 2
b1 4
#135
b10111011 !
b10111011 H
0"
1#
1-
#140
b0 F
1E
0D
b10000 I
0-
b101 7
b10000000000000 ,
b10000000000000 :
b10000000000000 R
b0 6
b0 4
#145
b10111011 F
0E
1D
b0 !
b0 H
1"
0#
1-
#150
0-
b10 2
b1 4
#155
b10111011 !
b10111011 H
0"
1#
1-
#160
b0 F
1E
0D
b11000 I
0-
b110 7
10
b11001100 /
b11001100 ;
b11000000000000 ,
b11000000000000 :
b11001100 S
b11000000000000 T
b0 4
#165
0E
1D
b0 !
b0 H
1"
0#
1-
#170
0-
b11 9
b1 6
#175
0"
1#
1-
#180
b11001100 F
0-
b111 7
00
b11000000000000 R
#185
b11001100 !
b11001100 H
1-
#190
0-
b10 1
b1 3
#195
1-
#200
b0 F
1E
0D
b10000000 I
0-
b1000 7
b10000000000000000 ,
b10000000000000000 :
b10000000000000000 R
b0 6
b0 3
#205
b11001100 F
0E
1D
b0 !
b0 H
1"
0#
1-
#210
0-
b11 2
b1 4
#215
b11001100 !
b11001100 H
0"
1#
1-
#220
b0 F
1E
0D
b1 G
0-
b1001 7
b10000000000100000 ,
b10000000000100000 :
b10000000000100000 R
b100000 K
#225
bx F
0E
1D
b0 !
b0 H
1"
0#
1-
#230
0-
b100 2
b10 4
#235
bx !
bx H
0"
1#
1-
#240
b0 F
1E
0D
b10 G
0-
b1010 7
b10000000001000000 ,
b10000000001000000 :
b10000000001000000 R
b1000000 K
#245
bx F
0E
1D
b0 !
b0 H
1"
0#
1-
#250
0-
b101 2
b11 4
#255
bx !
bx H
0"
1#
1-
#260
b0 F
1E
0D
b11 G
0-
b1011 7
b10000000001100000 ,
b10000000001100000 :
b10000000001100000 R
b1100000 K
#265
bx F
0E
1D
b0 !
b0 H
1"
0#
1-
#270
0-
b110 2
b100 4
#275
bx !
bx H
0"
1#
1-
#280
b0 F
1E
0D
b100 G
0-
b1100 7
b10000000010000000 ,
b10000000010000000 :
b10000000010000000 R
b10000000 K
#285
bx F
0E
1D
b0 !
b0 H
1"
0#
1-
#290
0-
b111 2
b101 4
#295
bx !
bx H
0"
1#
1-
#300
b0 F
1E
0D
b101 G
0-
b1101 7
b10000000010100000 ,
b10000000010100000 :
b10000000010100000 R
b10100000 K
#305
bx F
0E
1D
b0 !
b0 H
1"
0#
1-
#310
0-
b1000 2
b110 4
#315
bx !
bx H
0"
1#
1-
#320
b0 F
1E
0D
b110 G
0-
b1110 7
b10000000011000000 ,
b10000000011000000 :
b10000000011000000 R
b11000000 K
#325
bx F
0E
1D
b0 !
b0 H
1"
0#
1-
#330
0-
b1001 2
b111 4
#335
bx !
bx H
0"
1#
1-
#340
b0 F
1E
0D
b111 G
0-
b1111 7
b10000000011100000 ,
b10000000011100000 :
b10000000011100000 R
b11100000 K
#345
bx F
0E
1D
b0 !
b0 H
1"
0#
1-
#350
0-
b1010 2
b1000 4
#355
bx !
bx H
0"
1#
1-
#360
b0 F
1E
0D
b1000 G
0-
b10000 7
b10000000100000000 ,
b10000000100000000 :
b10000000100000000 R
b100000000 K
#365
bx F
0E
1D
b0 !
b0 H
1"
0#
1-
#370
0-
b1011 2
b1001 4
#375
bx !
bx H
0"
1#
1-
#380
b0 F
1E
0D
b1001 G
0-
b10001 7
b10000000100100000 ,
b10000000100100000 :
b10000000100100000 R
b100100000 K
#385
bx F
0E
1D
b0 !
b0 H
1"
0#
1-
#390
0-
b1100 2
b1010 4
#395
bx !
bx H
0"
1#
1-
#400
b0 F
1E
0D
b1010 G
0-
b10010 7
b10000000101000000 ,
b10000000101000000 :
b10000000101000000 R
b101000000 K
#405
bx F
0E
1D
b0 !
b0 H
1"
0#
1-
#410
0-
b1101 2
b1011 4
#415
bx !
bx H
0"
1#
1-
#420
b0 F
1E
0D
b1011 G
0-
b10011 7
b10000000101100000 ,
b10000000101100000 :
b10000000101100000 R
b101100000 K
#425
bx F
0E
1D
b0 !
b0 H
1"
0#
1-
#430
0-
b1110 2
b1100 4
#435
bx !
bx H
0"
1#
1-
#440
b0 F
1E
0D
b1100 G
0-
b10100 7
b10000000110000000 ,
b10000000110000000 :
b10000000110000000 R
b110000000 K
#445
bx F
0E
1D
b0 !
b0 H
1"
0#
1-
#450
0-
b1111 2
b1101 4
#455
bx !
bx H
0"
1#
1-
#460
b0 F
1E
0D
b1101 G
0-
b10101 7
b10000000110100000 ,
b10000000110100000 :
b10000000110100000 R
b110100000 K
#465
bx F
0E
1D
b0 !
b0 H
1"
0#
1-
#470
0-
b10000 2
b1110 4
#475
bx !
bx H
0"
1#
1-
#480
b0 F
1E
0D
b1110 G
0-
b10110 7
b10000000111000000 ,
b10000000111000000 :
b10000000111000000 R
b111000000 K
#485
bx F
0E
1D
b0 !
b0 H
1"
0#
1-
#490
0-
b10001 2
b1111 4
#495
bx !
bx H
0"
1#
1-
#500
b0 F
1E
0D
b1111 G
0-
b10111 7
b10000000111100000 ,
b10000000111100000 :
b10000000111100000 R
b111100000 K
#505
bx F
0E
1D
b0 !
b0 H
1"
0#
1-
#510
0-
b10010 2
b10000 4
#515
bx !
bx H
0"
1#
1-
#520
b0 F
1E
0D
b0 G
b10000001 I
0-
b11000 7
b10000001000000000 ,
b10000001000000000 :
b10000001000000000 R
b1000000000 K
#525
b11001100 F
0E
1D
b0 !
b0 H
1"
0#
1-
#530
0-
b10011 2
b10001 4
#535
b11001100 !
b11001100 H
0"
1#
1-
#540
b0 F
1E
0D
b1 G
0-
b11001 7
b10000001000100000 ,
b10000001000100000 :
b10000001000100000 R
b1000100000 K
#545
bx F
0E
1D
b0 !
b0 H
1"
0#
1-
#550
0-
b10100 2
b10010 4
#555
bx !
bx H
0"
1#
1-
#560
b0 F
1E
0D
b10 G
0-
b11010 7
b10000001001000000 ,
b10000001001000000 :
b10000001001000000 R
b1001000000 K
#565
bx F
0E
1D
b0 !
b0 H
1"
0#
1-
#570
0-
b10101 2
b10011 4
#575
bx !
bx H
0"
1#
1-
#580
b0 F
1E
0D
b11 G
0-
b11011 7
b10000001001100000 ,
b10000001001100000 :
b10000001001100000 R
b1001100000 K
#585
bx F
0E
1D
b0 !
b0 H
1"
0#
1-
#590
0-
b10110 2
b10100 4
#595
bx !
bx H
0"
1#
1-
#600
b0 F
1E
0D
b100 G
0-
b11100 7
b10000001010000000 ,
b10000001010000000 :
b10000001010000000 R
b1010000000 K
#605
bx F
0E
1D
b0 !
b0 H
1"
0#
1-
#610
0-
b10111 2
b10101 4
#615
bx !
bx H
0"
1#
1-
#620
b0 F
1E
0D
b101 G
0-
b11101 7
b10000001010100000 ,
b10000001010100000 :
b10000001010100000 R
b1010100000 K
#625
bx F
0E
1D
b0 !
b0 H
1"
0#
1-
#630
0-
b11000 2
b10110 4
#635
bx !
bx H
0"
1#
1-
#640
b0 F
1E
0D
b110 G
0-
b11110 7
b10000001011000000 ,
b10000001011000000 :
b10000001011000000 R
b1011000000 K
#645
bx F
0E
1D
b0 !
b0 H
1"
0#
1-
#650
0-
b11001 2
b10111 4
#655
bx !
bx H
0"
1#
1-
#660
b0 F
1E
0D
b111 G
0-
b11111 7
b10000001011100000 ,
b10000001011100000 :
b10000001011100000 R
b1011100000 K
#665
bx F
0E
1D
b0 !
b0 H
1"
0#
1-
#670
0-
b11010 2
b11000 4
#675
bx !
bx H
0"
1#
1-
#680
b0 F
1E
0D
b1000 G
0-
b100000 7
b10000001100000000 ,
b10000001100000000 :
b10000001100000000 R
b1100000000 K
#685
bx F
0E
1D
b0 !
b0 H
1"
0#
1-
#690
0-
b11011 2
b11001 4
#695
bx !
bx H
0"
1#
1-
#700
b0 F
1E
0D
b1001 G
0-
b100001 7
b10000001100100000 ,
b10000001100100000 :
b10000001100100000 R
b1100100000 K
#705
bx F
0E
1D
b0 !
b0 H
1"
0#
1-
#710
0-
b11100 2
b11010 4
#715
bx !
bx H
0"
1#
1-
#720
b0 F
1E
0D
b1010 G
0-
b100010 7
b10000001101000000 ,
b10000001101000000 :
b10000001101000000 R
b1101000000 K
#725
bx F
0E
1D
b0 !
b0 H
1"
0#
1-
#730
0-
b11101 2
b11011 4
#735
bx !
bx H
0"
1#
1-
#740
b0 F
1E
0D
b1011 G
0-
b100011 7
b10000001101100000 ,
b10000001101100000 :
b10000001101100000 R
b1101100000 K
#745
bx F
0E
1D
b0 !
b0 H
1"
0#
1-
#750
0-
b11110 2
b11100 4
#755
bx !
bx H
0"
1#
1-
#760
b0 F
1E
0D
b1100 G
0-
b100100 7
b10000001110000000 ,
b10000001110000000 :
b10000001110000000 R
b1110000000 K
#765
bx F
0E
1D
b0 !
b0 H
1"
0#
1-
#770
0-
b11111 2
b11101 4
#775
bx !
bx H
0"
1#
1-
#780
b0 F
1E
0D
b1101 G
0-
b100101 7
b10000001110100000 ,
b10000001110100000 :
b10000001110100000 R
b1110100000 K
#785
bx F
0E
1D
b0 !
b0 H
1"
0#
1-
#790
0-
b100000 2
b11110 4
#795
bx !
bx H
0"
1#
1-
#800
b0 F
1E
0D
b1110 G
0-
b100110 7
b10000001111000000 ,
b10000001111000000 :
b10000001111000000 R
b1111000000 K
#805
bx F
0E
1D
b0 !
b0 H
1"
0#
1-
#810
0-
b100001 2
b11111 4
#815
bx !
bx H
0"
1#
1-
#820
b0 F
1E
0D
b1111 G
0-
b100111 7
b10000001111100000 ,
b10000001111100000 :
b10000001111100000 R
b1111100000 K
#825
bx F
0E
1D
b0 !
b0 H
1"
0#
1-
#830
0-
b100010 2
b100000 4
#835
bx !
bx H
0"
1#
1-
#840
b0 F
1E
0D
b0 G
b100000000 I
0-
b101000 7
b100000000000000000 ,
b100000000000000000 :
b100000000000000000 R
b0 4
b10000000000 K
#845
b11001100 F
0E
1D
b0 !
b0 H
1"
0#
1-
#850
0-
b100011 2
b1 4
#855
b11001100 !
b11001100 H
0"
1#
1-
#860
b0 F
1E
0D
b1 G
0-
b101001 7
b100000000000100000 ,
b100000000000100000 :
b100000000000100000 R
b100000 L
#865
bx F
0E
1D
b0 !
b0 H
1"
0#
1-
#870
0-
b100100 2
b10 4
#875
bx !
bx H
0"
1#
1-
#880
b0 F
1E
0D
b10 G
0-
b101010 7
b100000000001000000 ,
b100000000001000000 :
b100000000001000000 R
b1000000 L
#885
bx F
0E
1D
b0 !
b0 H
1"
0#
1-
#890
0-
b100101 2
b11 4
#895
bx !
bx H
0"
1#
1-
#900
b0 F
1E
0D
b11 G
0-
b101011 7
b100000000001100000 ,
b100000000001100000 :
b100000000001100000 R
b1100000 L
#905
bx F
0E
1D
b0 !
b0 H
1"
0#
1-
#910
0-
b100110 2
b100 4
#915
bx !
bx H
0"
1#
1-
#920
b0 F
1E
0D
b100 G
0-
b101100 7
b100000000010000000 ,
b100000000010000000 :
b100000000010000000 R
b10000000 L
#925
bx F
0E
1D
b0 !
b0 H
1"
0#
1-
#930
0-
b100111 2
b101 4
#935
bx !
bx H
0"
1#
1-
#940
b0 F
1E
0D
b101 G
0-
b101101 7
b100000000010100000 ,
b100000000010100000 :
b100000000010100000 R
b10100000 L
#945
bx F
0E
1D
b0 !
b0 H
1"
0#
1-
#950
0-
b101000 2
b110 4
#955
bx !
bx H
0"
1#
1-
#960
b0 F
1E
0D
b110 G
0-
b101110 7
b100000000011000000 ,
b100000000011000000 :
b100000000011000000 R
b11000000 L
#965
bx F
0E
1D
b0 !
b0 H
1"
0#
1-
#970
0-
b101001 2
b111 4
#975
bx !
bx H
0"
1#
1-
#980
b0 F
1E
0D
b111 G
0-
b101111 7
b100000000011100000 ,
b100000000011100000 :
b100000000011100000 R
b11100000 L
#985
bx F
0E
1D
b0 !
b0 H
1"
0#
1-
#990
0-
b101010 2
b1000 4
#995
bx !
bx H
0"
1#
1-
#1000
b0 F
1E
0D
b1000 G
0-
b110000 7
b100000000100000000 ,
b100000000100000000 :
b100000000100000000 R
b100000000 L
#1005
bx F
0E
1D
b0 !
b0 H
1"
0#
1-
#1010
0-
b101011 2
b1001 4
#1015
bx !
bx H
0"
1#
1-
#1020
b0 F
1E
0D
b1001 G
0-
b110001 7
b100000000100100000 ,
b100000000100100000 :
b100000000100100000 R
b100100000 L
#1025
bx F
0E
1D
b0 !
b0 H
1"
0#
1-
#1030
0-
b101100 2
b1010 4
#1035
bx !
bx H
0"
1#
1-
#1040
b0 F
1E
0D
b1010 G
0-
b110010 7
b100000000101000000 ,
b100000000101000000 :
b100000000101000000 R
b101000000 L
#1045
bx F
0E
1D
b0 !
b0 H
1"
0#
1-
#1050
0-
b101101 2
b1011 4
#1055
bx !
bx H
0"
1#
1-
#1060
b0 F
1E
0D
b1011 G
0-
b110011 7
b100000000101100000 ,
b100000000101100000 :
b100000000101100000 R
b101100000 L
#1065
bx F
0E
1D
b0 !
b0 H
1"
0#
1-
#1070
0-
b101110 2
b1100 4
#1075
bx !
bx H
0"
1#
1-
#1080
b0 F
1E
0D
b1100 G
0-
b110100 7
b100000000110000000 ,
b100000000110000000 :
b100000000110000000 R
b110000000 L
#1085
bx F
0E
1D
b0 !
b0 H
1"
0#
1-
#1090
0-
b101111 2
b1101 4
#1095
bx !
bx H
0"
1#
1-
#1100
b0 F
1E
0D
b1101 G
0-
b110101 7
b100000000110100000 ,
b100000000110100000 :
b100000000110100000 R
b110100000 L
#1105
bx F
0E
1D
b0 !
b0 H
1"
0#
1-
#1110
0-
b110000 2
b1110 4
#1115
bx !
bx H
0"
1#
1-
#1120
b0 F
1E
0D
b1110 G
0-
b110110 7
b100000000111000000 ,
b100000000111000000 :
b100000000111000000 R
b111000000 L
#1125
bx F
0E
1D
b0 !
b0 H
1"
0#
1-
#1130
0-
b110001 2
b1111 4
#1135
bx !
bx H
0"
1#
1-
#1140
b0 F
1E
0D
b1111 G
0-
b110111 7
b100000000111100000 ,
b100000000111100000 :
b100000000111100000 R
b111100000 L
#1145
bx F
0E
1D
b0 !
b0 H
1"
0#
1-
#1150
0-
b110010 2
b10000 4
#1155
bx !
bx H
0"
1#
1-
#1160
b0 F
1E
0D
b0 G
b110000000 I
0-
b111000 7
b110000000000000000 ,
b110000000000000000 :
b110000000000000000 R
b0 4
b1000000000 L
#1165
b11001100 F
0E
1D
b0 !
b0 H
1"
0#
1-
#1170
0-
b110011 2
b1 4
#1175
b11001100 !
b11001100 H
0"
1#
1-
#1180
bx F
b1000 C
0-
b111001 7
b110000000000001000 ,
b110000000000001000 :
b110000000000001000 R
b1000 M
#1185
bx !
bx H
1-
#1190
0-
b11 1
b1 3
#1195
1-
#1200
b10000 C
0-
b111010 7
b110000000000010000 ,
b110000000000010000 :
b110000000000010000 R
b10000 M
#1205
1-
#1210
0-
b100 1
b10 3
#1215
1-
#1220
b11000 C
0-
b111011 7
b110000000000011000 ,
b110000000000011000 :
b110000000000011000 R
b11000 M
#1225
1-
#1230
0-
b101 1
b11 3
#1235
1-
#1240
b0 F
1E
0D
b0 C
b1 G
0-
b111100 7
b110000000000100000 ,
b110000000000100000 :
b110000000000100000 R
b100000 M
#1245
bx F
0E
1D
b0 !
b0 H
1"
0#
1-
#1250
0-
b110100 2
b10 4
#1255
bx !
bx H
0"
1#
1-
#1260
b1000 C
0-
b111101 7
b110000000000101000 ,
b110000000000101000 :
b110000000000101000 R
b101000 M
#1265
1-
#1270
0-
b110 1
b100 3
#1275
1-
#1280
b10000 C
0-
b111110 7
b110000000000110000 ,
b110000000000110000 :
b110000000000110000 R
b110000 M
#1285
1-
#1290
0-
b111 1
b101 3
#1295
1-
#1300
b11000 C
0-
b111111 7
b110000000000111000 ,
b110000000000111000 :
b110000000000111000 R
b111000 M
#1305
1-
#1310
0-
b1000 1
b110 3
#1315
1-
#1320
b0 F
1E
0D
b0 C
b10 G
0-
b1000000 7
b110000000001000000 ,
b110000000001000000 :
b110000000001000000 R
b1000000 M
#1325
bx F
0E
1D
b0 !
b0 H
1"
0#
1-
#1330
0-
b110101 2
b11 4
#1335
bx !
bx H
0"
1#
1-
#1340
b1000 C
0-
b1000001 7
b110000000001001000 ,
b110000000001001000 :
b110000000001001000 R
b1001000 M
#1345
1-
#1350
0-
b1001 1
b111 3
#1355
1-
#1360
b10000 C
0-
b1000010 7
b110000000001010000 ,
b110000000001010000 :
b110000000001010000 R
b1010000 M
#1365
1-
#1370
0-
b1010 1
b1000 3
#1375
1-
#1380
b11000 C
0-
b1000011 7
b110000000001011000 ,
b110000000001011000 :
b110000000001011000 R
b1011000 M
#1385
1-
#1390
0-
b1011 1
b1001 3
#1395
1-
#1400
b0 F
1E
0D
b0 C
b11 G
0-
b1000100 7
b110000000001100000 ,
b110000000001100000 :
b110000000001100000 R
b1100000 M
#1405
bx F
0E
1D
b0 !
b0 H
1"
0#
1-
#1410
0-
b110110 2
b100 4
#1415
bx !
bx H
0"
1#
1-
#1420
b1000 C
0-
b1000101 7
b110000000001101000 ,
b110000000001101000 :
b110000000001101000 R
b1101000 M
#1425
1-
