iceBlinkPico-main/projects/cachef/caches/direct_mapped_cache.sv
// direct_mapped_cache.sv

module direct_mapped_cache #(
    parameter CACHE_SIZE = 256,        // Total size of the cache in bytes
    parameter BLOCK_SIZE = 16,         // Size of each cache block in bytes
    parameter ASSOC = 1,               // Level of associativity (1 for direct-mapped)
    parameter ADDR_WIDTH = 32,         // Bit-width of the address
    parameter DATA_WIDTH = 32          // Bit-width of data in each cache line
) (
    input logic clk,
    input logic rst,
    input logic [ADDR_WIDTH-1:0] address,
    input logic read_enable,
    input logic write_enable,
    input logic [DATA_WIDTH-1:0] write_data,
    output logic [DATA_WIDTH-1:0] read_data,
    output logic hit,
    output logic miss
);

    // Number of cache lines
    localparam NUM_LINES = CACHE_SIZE / BLOCK_SIZE;
    
    // Calculate address breakdowns
    localparam INDEX_BITS = $clog2(NUM_LINES);
    localparam OFFSET_BITS = $clog2(BLOCK_SIZE);
    localparam TAG_BITS = ADDR_WIDTH - INDEX_BITS - OFFSET_BITS;
    
    // Cache storage - separate arrays instead of structs
    logic [NUM_LINES-1:0] valid;
    logic [TAG_BITS-1:0] tags [NUM_LINES-1:0];
    logic [DATA_WIDTH-1:0] data [NUM_LINES-1:0]; // Simplified to one word per line for now
    
    // Address components
    logic [TAG_BITS-1:0] tag;
    logic [INDEX_BITS-1:0] index;
    logic [OFFSET_BITS-1:0] offset;
    
    // Extract address fields
    always_comb begin
        offset = address[OFFSET_BITS-1:0];
        index = address[INDEX_BITS+OFFSET_BITS-1:OFFSET_BITS];
        tag = address[ADDR_WIDTH-1:INDEX_BITS+OFFSET_BITS];
    end
    
    always_ff @(posedge clk or posedge rst) begin
        if (rst) begin
            // Reset all cache entries
            for (int i = 0; i < NUM_LINES; i++) begin
                valid[i] <= 0;
                tags[i] <= 0;
                data[i] <= 0;
            end
            hit <= 0;
            miss <= 0;
            read_data <= 0;
        end else begin
            // Default values
            hit <= 0;
            miss <= 0;
            
            if (read_enable) begin
                // Read operation
                if (valid[index] && (tags[index] == tag)) begin
                    hit <= 1;
                    read_data <= data[index];
                end else begin
                    miss <= 1;
                    // On a real system, we'd fetch from memory here
                    // For simulation, we'll just indicate the miss
                end
            end else if (write_enable) begin
                // Write operation (write-through policy)
                if (valid[index] && (tags[index] == tag)) begin
                    hit <= 1;
                end else begin
                    miss <= 1;
                    valid[index] <= 1;
                    tags[index] <= tag;
                end
                // Write data to cache regardless (write-allocate)
                data[index] <= write_data;
            end
        end
    end
endmodule

iceBlinkPico-main/projects/cachef/testbenches/direct_mapped_cache_tb.sv
// direct_mapped_cache_tb.sv

module direct_mapped_cache_tb;
    // Default parameters
    parameter CACHE_SIZE = 256;        // Default values; can be overridden
    parameter BLOCK_SIZE = 16;
    parameter ASSOC = 1;               // Direct Mapped
    parameter ADDR_WIDTH = 32;         // Bit-width of address
    parameter DATA_WIDTH = 32;         // Bit-width of data

    // Signal declarations
    logic clk;
    logic rst;
    logic [ADDR_WIDTH-1:0] address;
    logic read_enable;
    logic write_enable;
    logic [DATA_WIDTH-1:0] write_data;
    logic [DATA_WIDTH-1:0] read_data;
    logic hit;
    logic miss;
    
    // Statistics
    int total_accesses = 0;
    int total_hits = 0;
    int total_misses = 0;

    // Instantiate the direct mapped cache
    direct_mapped_cache #(
        .CACHE_SIZE(CACHE_SIZE),
        .BLOCK_SIZE(BLOCK_SIZE),
        .ASSOC(ASSOC),
        .ADDR_WIDTH(ADDR_WIDTH),
        .DATA_WIDTH(DATA_WIDTH)
    ) dut (
        .clk(clk),
        .rst(rst),
        .address(address),
        .read_enable(read_enable),
        .write_enable(write_enable),
        .write_data(write_data),
        .read_data(read_data),
        .hit(hit),
        .miss(miss)
    );

    // Clock generation
    always #5 clk = ~clk;
    
    // Monitor hit/miss status
    always @(posedge clk) begin
        if (read_enable || write_enable) begin
            total_accesses++;
            if (hit) total_hits++;
            if (miss) total_misses++;
        end
    end

    initial begin
        // Initialize signals and dump waveform
        $dumpfile("direct_mapped_cache.vcd");
        $dumpvars(0, direct_mapped_cache_tb);
        
        clk = 0;
        rst = 1;
        write_enable = 0;
        read_enable = 0;
        address = 0;
        write_data = 0;
        
        #10 rst = 0; // Release reset after some time
        
        // Test 1: Sequential access pattern (good spatial locality)
        $display("Test 1: Sequential Access Pattern");
        for (int i = 0; i < 16; i++) begin
            // Write phase
            @(posedge clk);
            address = i * 16;  // Sequential addresses matching block size
            write_data = i + 100;
            write_enable = 1;
            read_enable = 0;
            @(posedge clk);
            write_enable = 0;
            
            // Read phase (should hit after first miss)
            @(posedge clk);
            read_enable = 1;
            @(posedge clk);
            read_enable = 0;
            
            $display("Address: %h, Write: %h, Read: %h, Hit: %b, Miss: %b", 
                    address, write_data, read_data, hit, miss);
        end
        
        // Test 2: Random access pattern (poor locality)
        $display("\nTest 2: Random Access Pattern");
        for (int i = 0; i < 16; i++) begin
            @(posedge clk);
            // Use a pseudo-random pattern
            address = ((i * 97) % 64) * 16;  // Create some conflicts
            write_data = i + 200;
            write_enable = 1;
            read_enable = 0;
            @(posedge clk);
            write_enable = 0;
            
            @(posedge clk);
            read_enable = 1;
            @(posedge clk);
            read_enable = 0;
            
            $display("Address: %h, Write: %h, Read: %h, Hit: %b, Miss: %b", 
                    address, write_data, read_data, hit, miss);
        end
        
        // Report statistics
        $display("\nCache Statistics:");
        $display("Total Accesses: %d", total_accesses);
        $display("Total Hits: %d (%.2f%%)", total_hits, 100.0*total_hits/total_accesses);
        $display("Total Misses: %d (%.2f%%)", total_misses, 100.0*total_misses/total_accesses);
        
        #50 $finish;
    end
endmodule

iceBlinkPico-main/projects/cachef/direct_mapped_cache.vcd
$date
	Mon Apr 28 12:39:26 2025
$end
$version
	Icarus Verilog
$end
$timescale
	1s
$end
$scope module direct_mapped_cache_tb $end
$var wire 32 ! read_data [31:0] $end
$var wire 1 " miss $end
$var wire 1 # hit $end
$var parameter 32 $ ADDR_WIDTH $end
$var parameter 32 % ASSOC $end
$var parameter 32 & BLOCK_SIZE $end
$var parameter 32 ' CACHE_SIZE $end
$var parameter 32 ( DATA_WIDTH $end
$var reg 32 ) address [31:0] $end
$var reg 1 * clk $end
$var reg 1 + read_enable $end
$var reg 1 , rst $end
$var reg 32 - write_data [31:0] $end
$var reg 1 . write_enable $end
$var integer 32 / total_accesses [31:0] $end
$var integer 32 0 total_hits [31:0] $end
$var integer 32 1 total_misses [31:0] $end
$scope module dut $end
$var wire 32 2 address [31:0] $end
$var wire 1 * clk $end
$var wire 1 + read_enable $end
$var wire 1 , rst $end
$var wire 32 3 write_data [31:0] $end
$var wire 1 . write_enable $end
$var parameter 32 4 ADDR_WIDTH $end
$var parameter 32 5 ASSOC $end
$var parameter 32 6 BLOCK_SIZE $end
$var parameter 32 7 CACHE_SIZE $end
$var parameter 32 8 DATA_WIDTH $end
$var parameter 32 9 INDEX_BITS $end
$var parameter 32 : NUM_LINES $end
$var parameter 32 ; OFFSET_BITS $end
$var parameter 34 < TAG_BITS $end
$var reg 1 # hit $end
$var reg 4 = index [3:0] $end
$var reg 1 " miss $end
$var reg 4 > offset [3:0] $end
$var reg 32 ? read_data [31:0] $end
$var reg 24 @ tag [23:0] $end
$var reg 16 A valid [15:0] $end
$scope begin $ivl_for_loop0 $end
$var integer 32 B i [31:0] $end
$upscope $end
$upscope $end
$scope begin $ivl_for_loop1 $end
$var integer 32 C i [31:0] $end
$upscope $end
$scope begin $ivl_for_loop2 $end
$var integer 32 D i [31:0] $end
$upscope $end
$upscope $end
$enddefinitions $end
$comment Show the parameter values. $end
$dumpall
b11000 <
b100 ;
b10000 :
b100 9
b100000 8
b100000000 7
b10000 6
b1 5
b100000 4
b100000 (
b100000000 '
b10000 &
b1 %
b100000 $
$end
#0
$dumpvars
b0 D
b0 C
b10000 B
b0 A
b0 @
b0 ?
b0 >
b0 =
b0 3
b0 2
b0 1
b0 0
b0 /
0.
b0 -
1,
0+
0*
b0 )
0#
0"
b0 !
$end
#5
b10000 B
1*
#10
0*
0,
#15
b1 A
1"
b1 /
1.
b1100100 -
b1100100 3
1*
#20
0*
#25
0"
0.
b1 1
b10 /
1*
#30
0*
#35
b1100100 !
b1100100 ?
1#
b11 /
1+
1*
#40
0*
#45
0#
b1 C
0+
b1 0
b100 /
1*
#50
0*
#55
1#
b1 =
b101 /
1.
b1100101 -
b1100101 3
b10000 )
b10000 2
1*
#60
0*
#65
0#
0.
b10 0
b110 /
1*
#70
0*
#75
1"
b111 /
1+
1*
#80
0*
#85
0"
b10 C
0+
b10 1
b1000 /
1*
#90
0*
#95
b11 A
1"
b10 =
b1001 /
1.
b1100110 -
b1100110 3
b100000 )
b100000 2
1*
#100
0*
#105
0"
0.
b11 1
b1010 /
1*
#110
0*
#115
1"
b1011 /
1+
1*
#120
0*
#125
0"
b11 C
0+
b100 1
b1100 /
1*
#130
0*
#135
b111 A
1"
b11 =
b1101 /
1.
b1100111 -
b1100111 3
b110000 )
b110000 2
1*
#140
0*
#145
0"
0.
b101 1
b1110 /
1*
#150
0*
#155
1"
b1111 /
1+
1*
#160
0*
#165
0"
b100 C
0+
b110 1
b10000 /
1*
#170
0*
#175
b1111 A
1"
b100 =
b10001 /
1.
b1101000 -
b1101000 3
b1000000 )
b1000000 2
1*
#180
0*
#185
0"
0.
b111 1
b10010 /
1*
#190
0*
#195
1"
b10011 /
1+
1*
#200
0*
#205
0"
b101 C
0+
b1000 1
b10100 /
1*
#210
0*
#215
b11111 A
1"
b101 =
b10101 /
1.
b1101001 -
b1101001 3
b1010000 )
b1010000 2
1*
#220
0*
#225
0"
0.
b1001 1
b10110 /
1*
#230
0*
#235
1"
b10111 /
1+
1*
#240
0*
#245
0"
b110 C
0+
b1010 1
b11000 /
1*
#250
0*
#255
b111111 A
1"
b110 =
b11001 /
1.
b1101010 -
b1101010 3
b1100000 )
b1100000 2
1*
#260
0*
#265
0"
0.
b1011 1
b11010 /
1*
#270
0*
#275
1"
b11011 /
1+
1*
#280
0*
#285
0"
b111 C
0+
b1100 1
b11100 /
1*
#290
0*
#295
b1111111 A
1"
b111 =
b11101 /
1.
b1101011 -
b1101011 3
b1110000 )
b1110000 2
1*
#300
0*
#305
0"
0.
b1101 1
b11110 /
1*
#310
0*
#315
1"
b11111 /
1+
1*
#320
0*
#325
0"
b1000 C
0+
b1110 1
b100000 /
1*
#330
0*
#335
b11111111 A
1"
b1000 =
b100001 /
1.
b1101100 -
b1101100 3
b10000000 )
b10000000 2
1*
#340
0*
#345
0"
0.
b1111 1
b100010 /
1*
#350
0*
#355
1"
b100011 /
1+
1*
#360
0*
#365
0"
b1001 C
0+
b10000 1
b100100 /
1*
#370
0*
#375
b111111111 A
1"
b1001 =
b100101 /
1.
b1101101 -
b1101101 3
b10010000 )
b10010000 2
1*
#380
0*
#385
0"
0.
b10001 1
b100110 /
1*
#390
0*
#395
1"
b100111 /
1+
1*
#400
0*
#405
0"
b1010 C
0+
b10010 1
b101000 /
1*
#410
0*
#415
b1111111111 A
1"
b1010 =
b101001 /
1.
b1101110 -
b1101110 3
b10100000 )
b10100000 2
1*
#420
0*
#425
0"
0.
b10011 1
b101010 /
1*
#430
0*
#435
1"
b101011 /
1+
1*
#440
0*
#445
0"
b1011 C
0+
b10100 1
b101100 /
1*
#450
0*
#455
b11111111111 A
1"
b1011 =
b101101 /
1.
b1101111 -
b1101111 3
b10110000 )
b10110000 2
1*
#460
0*
#465
0"
0.
b10101 1
b101110 /
1*
#470
0*
#475
1"
b101111 /
1+
1*
#480
0*
#485
0"
b1100 C
0+
b10110 1
b110000 /
1*
#490
0*
#495
b111111111111 A
1"
b1100 =
b110001 /
1.
b1110000 -
b1110000 3
b11000000 )
b11000000 2
1*
#500
0*
#505
0"
0.
b10111 1
b110010 /
1*
#510
0*
#515
1"
b110011 /
1+
1*
#520
0*
#525
0"
b1101 C
0+
b11000 1
b110100 /
1*
#530
0*
#535
b1111111111111 A
1"
b1101 =
b110101 /
1.
b1110001 -
b1110001 3
b11010000 )
b11010000 2
1*
#540
0*
#545
0"
0.
b11001 1
b110110 /
1*
#550
0*
#555
1"
b110111 /
1+
1*
#560
0*
#565
0"
b1110 C
0+
b11010 1
b111000 /
1*
#570
0*
#575
b11111111111111 A
1"
b1110 =
b111001 /
1.
b1110010 -
b1110010 3
b11100000 )
b11100000 2
1*
#580
0*
#585
0"
0.
b11011 1
b111010 /
1*
#590
0*
#595
1"
b111011 /
1+
1*
#600
0*
#605
0"
b1111 C
0+
b11100 1
b111100 /
1*
#610
0*
#615
b111111111111111 A
1"
b1111 =
b111101 /
1.
b1110011 -
b1110011 3
b11110000 )
b11110000 2
1*
#620
0*
#625
0"
0.
b11101 1
b111110 /
1*
#630
0*
#635
1"
b111111 /
1+
1*
#640
0*
#645
0"
b10000 C
0+
b11110 1
b1000000 /
1*
#650
0*
#655
b1111111111111111 A
1"
b0 =
b1000001 /
1.
b11001000 -
b11001000 3
b0 )
b0 2
1*
#660
0*
#665
0"
0.
b11111 1
b1000010 /
1*
#670
0*
#675
b1100101 !
b1100101 ?
1#
b1000011 /
1+
1*
#680
0*
#685
0#
b1 D
0+
b11 0
b1000100 /
1*
#690
0*
#695
1#
b10 @
b1 =
b1000101 /
1.
b11001001 -
b11001001 3
b1000010000 )
b1000010000 2
1*
#700
0*
#705
0#
0.
b100 0
b1000110 /
1*
#710
0*
#715
1"
b1000111 /
1+
1*
#720
0*
#725
0"
b10 D
0+
b100000 1
b1001000 /
1*
#730
0*
#735
1"
b0 @
b10 =
b1001001 /
1.
b11001010 -
b11001010 3
b100000 )
b100000 2
1*
#740
0*
#745
0"
0.
b100001 1
b1001010 /
1*
#750
0*
#755
b1100111 !
b1100111 ?
1#
b1001011 /
1+
1*
#760
0*
#765
0#
b11 D
0+
b101 0
b1001100 /
1*
#770
0*
#775
1#
b10 @
b11 =
b1001101 /
1.
b11001011 -
b11001011 3
b1000110000 )
b1000110000 2
1*
#780
0*
#785
0#
0.
b110 0
b1001110 /
1*
#790
0*
#795
1"
b1001111 /
1+
1*
#800
0*
#805
0"
b100 D
0+
b100010 1
b1010000 /
1*
#810
0*
#815
1"
b0 @
b100 =
b1010001 /
1.
b11001100 -
b11001100 3
b1000000 )
b1000000 2
1*
#820
0*
#825
0"
0.
b100011 1
b1010010 /
1*
#830
0*
#835
b1101001 !
b1101001 ?
1#
b1010011 /
1+
1*
#840
0*
#845
0#
b101 D
0+
b111 0
b1010100 /
1*
#850
0*
#855
1#
b10 @
b101 =
b1010101 /
1.
b11001101 -
b11001101 3
b1001010000 )
b1001010000 2
1*
#860
0*
#865
0#
0.
b1000 0
b1010110 /
1*
#870
0*
#875
1"
b1010111 /
1+
1*
#880
0*
#885
0"
b110 D
0+
b100100 1
b1011000 /
1*
#890
0*
#895
1"
b0 @
b110 =
b1011001 /
1.
b11001110 -
b11001110 3
b1100000 )
b1100000 2
1*
#900
0*
#905
0"
0.
b100101 1
b1011010 /
1*
#910
0*
#915
b1101011 !
b1101011 ?
1#
b1011011 /
1+
1*
#920
0*
#925
0#
b111 D
0+
b1001 0
b1011100 /
1*
#930
0*
#935
1#
b10 @
b111 =
b1011101 /
1.
b11001111 -
b11001111 3
b1001110000 )
b1001110000 2
1*
#940
0*
#945
0#
0.
b1010 0
b1011110 /
1*
#950
0*
#955
1"
b1011111 /
1+
1*
#960
0*
#965
0"
b1000 D
0+
b100110 1
b1100000 /
1*
#970
0*
#975
1"
b0 @
b1000 =
b1100001 /
1.
b11010000 -
b11010000 3
b10000000 )
b10000000 2
1*
#980
0*
#985
0"
0.
b100111 1
b1100010 /
1*
#990
0*
#995
b1101101 !
b1101101 ?
1#
b1100011 /
1+
1*
#1000
0*
#1005
0#
b1001 D
0+
b1011 0
b1100100 /
1*
#1010
0*
#1015
1#
b10 @
b1001 =
b1100101 /
1.
b11010001 -
b11010001 3
b1010010000 )
b1010010000 2
1*
#1020
0*
#1025
0#
0.
b1100 0
b1100110 /
1*
#1030
0*
#1035
1"
b1100111 /
1+
1*
#1040
0*
#1045
0"
b1010 D
0+
b101000 1
b1101000 /
1*
#1050
0*
#1055
1"
b0 @
b1010 =
b1101001 /
1.
b11010010 -
b11010010 3
b10100000 )
b10100000 2
1*
#1060
0*
#1065
0"
0.
b101001 1
b1101010 /
1*
#1070
0*
#1075
b1101111 !
b1101111 ?
1#
b1101011 /
1+
1*
#1080
0*
#1085
0#
b1011 D
0+
b1101 0
b1101100 /
1*
#1090
0*
#1095
1#
b10 @
b1011 =
b1101101 /
1.
b11010011 -
b11010011 3
b1010110000 )
b1010110000 2
1*
#1100
0*
#1105
0#
0.
b1110 0
b1101110 /
1*
#1110
0*
#1115
1"
b1101111 /
1+
1*
#1120
0*
#1125
0"
b1100 D
0+
b101010 1
b1110000 /
1*
#1130
0*
#1135
1"
b0 @
b1100 =
b1110001 /
1.
b11010100 -
b11010100 3
b11000000 )
b11000000 2
1*
#1140
0*
#1145
0"
0.
b101011 1
b1110010 /
1*
#1150
0*
#1155
b1110001 !
b1110001 ?
1#
b1110011 /
1+
1*
#1160
0*
#1165
0#
b1101 D
0+
b1111 0
b1110100 /
1*
#1170
0*
#1175
1#
b10 @
b1101 =
b1110101 /
1.
b11010101 -
b11010101 3
b1011010000 )
b1011010000 2
1*
#1180
0*
#1185
0#
0.
b10000 0
b1110110 /
1*
#1190
0*
#1195
1"
b1110111 /
1+
1*
#1200
0*
#1205
0"
b1110 D
0+
b101100 1
b1111000 /
1*
#1210
0*
#1215
1"
b0 @
b1110 =
b1111001 /
1.
b11010110 -
b11010110 3
b11100000 )
b11100000 2
1*
#1220
0*
#1225
0"
0.
b101101 1
b1111010 /
1*
#1230
0*
#1235
b1110011 !
b1110011 ?
1#
b1111011 /
1+
1*
#1240
0*
#1245
0#
b1111 D
0+
b10001 0
b1111100 /
1*
#1250
0*
#1255
1#
b10 @
b1111 =
b1111101 /
1.
b11010111 -
b11010111 3
b1011110000 )
b1011110000 2
1*
#1260
0*
#1265
0#
0.
b10010 0
b1111110 /
1*
#1270
0*
#1275
1"
b1111111 /
1+
1*
#1280
0*
#1285
0"
b10000 D
0+
b101110 1
b10000000 /
1*
