iceBlinkPico-main/projects/cachef/caches/direct_mapped_cache.sv
// direct_mapped_cache.sv

module direct_mapped_cache #(
    parameter CACHE_SIZE = 256, // Total cache size in bytes
    parameter BLOCK_SIZE = 16,   // Cache block size in bytes
    parameter ASSOC = 1          // Associativity (1 for direct-mapped)
)(
    input logic clk,
    input logic reset,
    input logic [31:0] addr,
    input logic [7:0] wr_data,
    input logic wr_en,
    output logic [7:0] rd_data,
    output logic hit,
    output logic miss
);

    localparam NUM_SETS = CACHE_SIZE / (BLOCK_SIZE * ASSOC);
    localparam BLOCK_OFFSET_WIDTH = $clog2(BLOCK_SIZE);
    localparam INDEX_WIDTH = $clog2(NUM_SETS);
    localparam TAG_WIDTH = 32 - INDEX_WIDTH - BLOCK_OFFSET_WIDTH;

    logic [7:0] cache_data [NUM_SETS-1:0][BLOCK_SIZE-1:0];
    logic [TAG_WIDTH-1:0] cache_tag [NUM_SETS-1:0];
    logic valid [NUM_SETS-1:0];

    logic [TAG_WIDTH-1:0] tag;
    logic [INDEX_WIDTH-1:0] index;
    logic [BLOCK_OFFSET_WIDTH-1:0] block_offset;

    always_comb begin
        tag = addr[31 : 32 - TAG_WIDTH];
        index = addr[32 - TAG_WIDTH - 1 : BLOCK_OFFSET_WIDTH];
        block_offset = addr[BLOCK_OFFSET_WIDTH-1 : 0];
    end

    logic current_hit;
    logic current_miss;
    logic [7:0] current_rd_data;

    always_comb begin
        current_hit = (valid[index] && (cache_tag[index] == tag));
        current_miss = ~current_hit;

        if (current_hit && !wr_en) 
            current_rd_data = cache_data[index][block_offset];
        else 
            current_rd_data = 8'b0; // Default data on miss/write
    end

    always_ff @(posedge clk or posedge reset) begin
        if (reset) begin
            for (int i = 0; i < NUM_SETS; i++) 
                valid[i] <= 0;

            hit <= 0;
            miss <= 0;
            rd_data <= 8'b0;
        end else begin
            hit <= current_hit;
            miss <= current_miss;
            rd_data <= current_rd_data;

            if (current_miss || wr_en) begin
                valid[index] <= 1;
                cache_tag[index] <= tag;

                if (wr_en) 
                    cache_data[index][block_offset] <= wr_data;
            end
        end
    end

endmodule

iceBlinkPico-main/projects/cachef/testbenches/direct_mapped_cache_tb.sv
// direct_mapped_cache_tb.sv

module direct_mapped_cache_tb;

    parameter CACHE_SIZE = 256;
    parameter BLOCK_SIZE = 16; // Block size set for tests
    parameter ASSOC = 1; // Direct-mapped

    localparam PERIOD = 10; // Clock period in ns
    localparam NUM_SETS = CACHE_SIZE / (BLOCK_SIZE * ASSOC);
    localparam BLOCK_OFFSET_WIDTH = $clog2(BLOCK_SIZE);
    localparam INDEX_WIDTH = $clog2(NUM_SETS);
    localparam TAG_WIDTH = 32 - INDEX_WIDTH - BLOCK_OFFSET_WIDTH;

    logic clk;
    logic reset;
    logic [31:0] addr;
    logic [7:0] wr_data;
    logic wr_en;
    logic [7:0] rd_data;
    logic hit;
    logic miss;

     // Initial block to display parameters
    initial begin
        $display("Simulation Parameters:");
        $display("CACHE_SIZE = %0d", CACHE_SIZE);
        $display("BLOCK_SIZE = %0d", BLOCK_SIZE);
        $display("ASSOC = %0d", ASSOC);
        $display("NUM_SETS = %0d", NUM_SETS);
        $display("BLOCK_OFFSET_WIDTH = %0d", BLOCK_OFFSET_WIDTH);
        $display("INDEX_WIDTH = %0d", INDEX_WIDTH);
        $display("TAG_WIDTH = %0d", TAG_WIDTH);
    end

    // Instantiate the Cache Module
    direct_mapped_cache #(
        .CACHE_SIZE(CACHE_SIZE),
        .BLOCK_SIZE(BLOCK_SIZE),
        .ASSOC(ASSOC)
    ) dut (
        .clk(clk),
        .reset(reset),
        .addr(addr),
        .wr_data(wr_data),
        .wr_en(wr_en),
        .rd_data(rd_data),
        .hit(hit),
        .miss(miss)
    );

    // Clock Generation
    initial begin
        clk = 0;
        forever #(PERIOD/2) clk = ~clk;
    end

    // Metrics Counters
    integer total_accesses = 0;
    integer read_hits = 0;
    integer read_misses = 0;
    integer write_hits = 0;
    integer write_misses = 0;

    // Temporary counters for each test
    integer test_read_hits;
    integer test_read_misses;
    integer test_write_hits;
    integer test_write_misses;

    // Read operation task
    task read_access(input [31:0] read_addr);
        begin
            addr = read_addr;
            wr_en = 0;
            total_accesses++;
            #(PERIOD);
            if (hit) begin
                test_read_hits++;
                read_hits++;
            end else begin
                test_read_misses++;
                read_misses++;
            end
            #(PERIOD);
        end
    endtask

    // Write operation task
    task write_access(input [31:0] write_addr, input [7:0] data_to_write);
        begin
            addr = write_addr;
            wr_data = data_to_write;
            wr_en = 1;
            total_accesses++;
            #(PERIOD);
            if (miss) begin
                test_write_misses++;
                write_misses++;
            end else begin
                test_write_hits++;
                write_hits++;
            end
            #(PERIOD);
        end
    endtask

    // Function to display test results
    task display_test_results();
        $display("Test Results: Read Hits: %0d, Read Misses: %0d, Write Hits: %0d, Write Misses: %0d", 
            test_read_hits, test_read_misses, test_write_hits, test_write_misses);
        
        // Reset temporary counters for the next test
        test_read_hits = 0;
        test_read_misses = 0;
        test_write_hits = 0;
        test_write_misses = 0;
    endtask

    initial begin
        // Reset the cache
        $display("--- Resetting Cache ---");
        reset = 1;
        wr_en = 0;
        addr = 32'b0;
        wr_data = 8'b0;
        #(PERIOD * 5); // Hold reset
        reset = 0;
        #(PERIOD);

        // Initialize temporary counters
        test_read_hits = 0;
        test_read_misses = 0;
        test_write_hits = 0;
        test_write_misses = 0;

        // Basic Test Cases
        $display("--- Basic Test 1: Initial Write ---");
        write_access(32'h0000_1000, 8'hAA);
        
        $display("--- Basic Test 2: Read After Write ---");
        read_access(32'h0000_1000);
        display_test_results(); // Display totals after the test

        $display("--- Basic Test 3: Conflict Write ---");
        write_access(32'h0000_2000, 8'hBB);
        
        $display("--- Basic Test 4: Read Original Address After Conflict ---");
        read_access(32'h0000_1000);
        display_test_results(); // Display totals after the test
        
        $display("--- Basic Test 5: Read Conflict Address ---");
        read_access(32'h0000_2000);
        display_test_results(); // Display totals after the test
        
        $display("--- Basic Test 6: Write to a Different Set ---");
        write_access(32'h0000_3000, 8'hCC);
        
        $display("--- Basic Test 7: Read from New Set ---");
        read_access(32'h0000_3000);
        display_test_results(); // Display totals after the test

        // Test Cases
        $display("--- Test 8: Sequential Read Access ---");
        for (int i = 0; i < NUM_SETS * BLOCK_SIZE * 2; i = i + BLOCK_SIZE) begin 
            read_access(32'h0001_0000 + i);
        end
        display_test_results(); // Display totals after the test

        $display("--- Test 9: Strided Read Access (Stride = Block Size) ---");
        for (int i = 0; i < NUM_SETS * BLOCK_SIZE; i = i + BLOCK_SIZE) begin
            read_access(32'h0002_0000 + i);
        end
        display_test_results(); // Display totals after the test

        $display("--- Test 10: Strided Read Access (Stride < Block Size) ---");
        for (int i = 0; i < NUM_SETS * BLOCK_SIZE; i = i + (BLOCK_SIZE / 4)) begin 
            read_access(32'h0003_0000 + i);
        end
        display_test_results(); // Display totals after the test

        $display("--- Test 11: Sequential Write Access ---");
        for (int i = 0; i < NUM_SETS * BLOCK_SIZE; i = i + BLOCK_SIZE) begin
            write_access(32'h0004_0000 + i, 8'hEE);
        end
        display_test_results(); // Display totals after the test

        $display("--- Test 12: Read Back Sequential Writes ---");
        for (int i = 0; i < NUM_SETS * BLOCK_SIZE; i = i + BLOCK_SIZE) begin
            read_access(32'h0004_0000 + i);
        end
        display_test_results(); // Display totals after the test

        $display("--- Test 13: Accesses within the same set, different offsets ---");
        for (int i = 0; i < BLOCK_SIZE; i++) begin
            write_access(32'h0005_0000 + i, 8'hF0 + i); // Write different data
        end
        for (int i = 0; i < BLOCK_SIZE; i++) begin
            read_access(32'h0005_0000 + i); // Read back
        end
        display_test_results(); // Display totals after the test

        $display("--- Test 14: Random Access ---");
        read_access(32'h0006_1234);
        write_access(32'h0007_5678, 8'h11);
        read_access(32'h0008_9ABC);
        read_access(32'h0007_5678);
        display_test_results(); // Display totals after the test

        // Final Metrics
        $display("--- Simulation Complete ---");
        $display("Total Accesses: %0d", total_accesses);
        $display("Total Read Hits: %0d", read_hits);
        $display("Total Read Misses: %0d", read_misses);
        $display("Total Write Hits: %0d", write_hits);
        $display("Total Write Misses: %0d", write_misses);

        $finish; // End simulation
    end

    // Waveform dumping
    initial begin
        $dumpfile("direct_mapped_cache.vcd");
        $dumpvars(0, direct_mapped_cache_tb);
    end

endmodule

iceBlinkPico-main/projects/cachef/direct_mapped_cache.vcd
$date
	Wed May  7 14:45:41 2025
$end
$version
	Icarus Verilog
$end
$timescale
	1s
$end
$scope module direct_mapped_cache_tb $end
$var wire 8 ! rd_data [7:0] $end
$var wire 1 " miss $end
$var wire 1 # hit $end
$var parameter 32 $ ASSOC $end
$var parameter 32 % BLOCK_OFFSET_WIDTH $end
$var parameter 32 & BLOCK_SIZE $end
$var parameter 32 ' CACHE_SIZE $end
$var parameter 32 ( INDEX_WIDTH $end
$var parameter 64 ) NUM_SETS $end
$var parameter 32 * PERIOD $end
$var parameter 34 + TAG_WIDTH $end
$var reg 32 , addr [31:0] $end
$var reg 1 - clk $end
$var reg 1 . reset $end
$var reg 8 / wr_data [7:0] $end
$var reg 1 0 wr_en $end
$var integer 32 1 read_hits [31:0] $end
$var integer 32 2 read_misses [31:0] $end
$var integer 32 3 test_read_hits [31:0] $end
$var integer 32 4 test_read_misses [31:0] $end
$var integer 32 5 test_write_hits [31:0] $end
$var integer 32 6 test_write_misses [31:0] $end
$var integer 32 7 total_accesses [31:0] $end
$var integer 32 8 write_hits [31:0] $end
$var integer 32 9 write_misses [31:0] $end
$scope module dut $end
$var wire 32 : addr [31:0] $end
$var wire 1 - clk $end
$var wire 1 . reset $end
$var wire 8 ; wr_data [7:0] $end
$var wire 1 0 wr_en $end
$var parameter 32 < ASSOC $end
$var parameter 32 = BLOCK_OFFSET_WIDTH $end
$var parameter 32 > BLOCK_SIZE $end
$var parameter 32 ? CACHE_SIZE $end
$var parameter 32 @ INDEX_WIDTH $end
$var parameter 64 A NUM_SETS $end
$var parameter 34 B TAG_WIDTH $end
$var reg 5 C block_offset [4:0] $end
$var reg 1 D current_hit $end
$var reg 1 E current_miss $end
$var reg 8 F current_rd_data [7:0] $end
$var reg 1 # hit $end
$var reg 2 G index [1:0] $end
$var reg 1 " miss $end
$var reg 8 H rd_data [7:0] $end
$var reg 25 I tag [24:0] $end
$scope begin $ivl_for_loop0 $end
$var integer 32 J i [31:0] $end
$upscope $end
$upscope $end
$scope begin $ivl_for_loop1 $end
$var integer 32 K i [31:0] $end
$upscope $end
$scope begin $ivl_for_loop2 $end
$var integer 32 L i [31:0] $end
$upscope $end
$scope begin $ivl_for_loop3 $end
$var integer 32 M i [31:0] $end
$upscope $end
$scope begin $ivl_for_loop4 $end
$var integer 32 N i [31:0] $end
$upscope $end
$scope begin $ivl_for_loop5 $end
$var integer 32 O i [31:0] $end
$upscope $end
$scope begin $ivl_for_loop6 $end
$var integer 32 P i [31:0] $end
$upscope $end
$scope begin $ivl_for_loop7 $end
$var integer 32 Q i [31:0] $end
$upscope $end
$scope task display_test_results $end
$upscope $end
$scope task read_access $end
$var reg 32 R read_addr [31:0] $end
$upscope $end
$scope task write_access $end
$var reg 8 S data_to_write [7:0] $end
$var reg 32 T write_addr [31:0] $end
$upscope $end
$upscope $end
$enddefinitions $end
$comment Show the parameter values. $end
$dumpall
b11001 B
b100 A
b10 @
b10000000 ?
b100000 >
b101 =
b1 <
b11001 +
b1010 *
b100 )
b10 (
b10000000 '
b100000 &
b101 %
b1 $
$end
#0
$dumpvars
bx T
bx S
bx R
b0 Q
b0 P
b0 O
b0 N
b0 M
b0 L
b0 K
b100 J
b0 I
b0 H
b0 G
b0 F
1E
0D
b0 C
b0 ;
b0 :
b0 9
b0 8
b0 7
bx 6
bx 5
bx 4
bx 3
b0 2
b0 1
00
b0 /
1.
0-
b0 ,
0#
0"
b0 !
$end
#5
b100 J
1-
#10
0-
#15
b100 J
1-
#20
0-
#25
b100 J
1-
#30
0-
#35
b100 J
1-
#40
0-
#45
b100 J
1-
#50
0-
0.
#55
bx F
0E
1D
1"
1-
#60
b0 F
1E
0D
b100000 I
0-
b1 7
10
b10101010 /
b10101010 ;
b1000000000000 ,
b1000000000000 :
b10101010 S
b1000000000000 T
b0 6
b0 5
b0 4
b0 3
#65
0E
1D
1-
#70
0-
b1 9
b1 6
#75
0"
1#
1-
#80
b10101010 F
0-
b10 7
00
b1000000000000 R
#85
b10101010 !
b10101010 H
1-
#90
0-
b1 1
b1 3
#95
1-
#100
b0 F
1E
0D
b1000000 I
0-
b11 7
10
b10111011 /
b10111011 ;
b10000000000000 ,
b10000000000000 :
b10111011 S
b10000000000000 T
b0 6
b0 3
#105
0E
1D
b0 !
b0 H
1"
0#
1-
#110
0-
b10 9
b1 6
#115
0"
1#
1-
#120
1E
0D
b100000 I
0-
b100 7
00
b1000000000000 ,
b1000000000000 :
#125
b10111011 F
0E
1D
1"
0#
1-
#130
0-
b1 2
b1 4
#135
b10111011 !
b10111011 H
0"
1#
1-
#140
b0 F
1E
0D
b1000000 I
0-
b101 7
b10000000000000 ,
b10000000000000 :
b10000000000000 R
b0 6
b0 4
#145
b10111011 F
0E
1D
b0 !
b0 H
1"
0#
1-
#150
0-
b10 2
b1 4
#155
b10111011 !
b10111011 H
0"
1#
1-
#160
b0 F
1E
0D
b1100000 I
0-
b110 7
10
b11001100 /
b11001100 ;
b11000000000000 ,
b11000000000000 :
b11001100 S
b11000000000000 T
b0 4
#165
0E
1D
b0 !
b0 H
1"
0#
1-
#170
0-
b11 9
b1 6
#175
0"
1#
1-
#180
b11001100 F
0-
b111 7
00
b11000000000000 R
#185
b11001100 !
b11001100 H
1-
#190
0-
b10 1
b1 3
#195
1-
#200
b0 F
1E
0D
b1000000000 I
0-
b1000 7
b10000000000000000 ,
b10000000000000000 :
b10000000000000000 R
b0 6
b0 3
#205
b11001100 F
0E
1D
b0 !
b0 H
1"
0#
1-
#210
0-
b11 2
b1 4
#215
b11001100 !
b11001100 H
0"
1#
1-
#220
b0 F
1E
0D
b1 G
0-
b1001 7
b10000000000100000 ,
b10000000000100000 :
b10000000000100000 R
b100000 K
#225
bx F
0E
1D
b0 !
b0 H
1"
0#
1-
#230
0-
b100 2
b10 4
#235
bx !
bx H
0"
1#
1-
#240
b0 F
1E
0D
b10 G
0-
b1010 7
b10000000001000000 ,
b10000000001000000 :
b10000000001000000 R
b1000000 K
#245
bx F
0E
1D
b0 !
b0 H
1"
0#
1-
#250
0-
b101 2
b11 4
#255
bx !
bx H
0"
1#
1-
#260
b0 F
1E
0D
b11 G
0-
b1011 7
b10000000001100000 ,
b10000000001100000 :
b10000000001100000 R
b1100000 K
#265
bx F
0E
1D
b0 !
b0 H
1"
0#
1-
#270
0-
b110 2
b100 4
#275
bx !
bx H
0"
1#
1-
#280
b0 F
1E
0D
b0 G
b1000000001 I
0-
b1100 7
b10000000010000000 ,
b10000000010000000 :
b10000000010000000 R
b10000000 K
#285
b11001100 F
0E
1D
b0 !
b0 H
1"
0#
1-
#290
0-
b111 2
b101 4
#295
b11001100 !
b11001100 H
0"
1#
1-
#300
b0 F
1E
0D
b1 G
0-
b1101 7
b10000000010100000 ,
b10000000010100000 :
b10000000010100000 R
b10100000 K
#305
bx F
0E
1D
b0 !
b0 H
1"
0#
1-
#310
0-
b1000 2
b110 4
#315
bx !
bx H
0"
1#
1-
#320
b0 F
1E
0D
b10 G
0-
b1110 7
b10000000011000000 ,
b10000000011000000 :
b10000000011000000 R
b11000000 K
#325
bx F
0E
1D
b0 !
b0 H
1"
0#
1-
#330
0-
b1001 2
b111 4
#335
bx !
bx H
0"
1#
1-
#340
b0 F
1E
0D
b11 G
0-
b1111 7
b10000000011100000 ,
b10000000011100000 :
b10000000011100000 R
b11100000 K
#345
bx F
0E
1D
b0 !
b0 H
1"
0#
1-
#350
0-
b1010 2
b1000 4
#355
bx !
bx H
0"
1#
1-
#360
b0 F
1E
0D
b0 G
b10000000000 I
0-
b10000 7
b100000000000000000 ,
b100000000000000000 :
b100000000000000000 R
b0 4
b100000000 K
#365
b11001100 F
0E
1D
b0 !
b0 H
1"
0#
1-
#370
0-
b1011 2
b1 4
#375
b11001100 !
b11001100 H
0"
1#
1-
#380
b0 F
1E
0D
b1 G
0-
b10001 7
b100000000000100000 ,
b100000000000100000 :
b100000000000100000 R
b100000 L
#385
bx F
0E
1D
b0 !
b0 H
1"
0#
1-
#390
0-
b1100 2
b10 4
#395
bx !
bx H
0"
1#
1-
#400
b0 F
1E
0D
b10 G
0-
b10010 7
b100000000001000000 ,
b100000000001000000 :
b100000000001000000 R
b1000000 L
#405
bx F
0E
1D
b0 !
b0 H
1"
0#
1-
#410
0-
b1101 2
b11 4
#415
bx !
bx H
0"
1#
1-
#420
b0 F
1E
0D
b11 G
0-
b10011 7
b100000000001100000 ,
b100000000001100000 :
b100000000001100000 R
b1100000 L
#425
bx F
0E
1D
b0 !
b0 H
1"
0#
1-
#430
0-
b1110 2
b100 4
#435
bx !
bx H
0"
1#
1-
#440
b0 F
1E
0D
b0 G
b11000000000 I
0-
b10100 7
b110000000000000000 ,
b110000000000000000 :
b110000000000000000 R
b0 4
b10000000 L
#445
b11001100 F
0E
1D
b0 !
b0 H
1"
0#
1-
#450
0-
b1111 2
b1 4
#455
b11001100 !
b11001100 H
0"
1#
1-
#460
bx F
b1000 C
0-
b10101 7
b110000000000001000 ,
b110000000000001000 :
b110000000000001000 R
b1000 M
#465
bx !
bx H
1-
#470
0-
b11 1
b1 3
#475
1-
#480
b10000 C
0-
b10110 7
b110000000000010000 ,
b110000000000010000 :
b110000000000010000 R
b10000 M
#485
1-
#490
0-
b100 1
b10 3
#495
1-
#500
b11000 C
0-
b10111 7
b110000000000011000 ,
b110000000000011000 :
b110000000000011000 R
b11000 M
#505
1-
#510
0-
b101 1
b11 3
#515
1-
#520
b0 F
1E
0D
b0 C
b1 G
0-
b11000 7
b110000000000100000 ,
b110000000000100000 :
b110000000000100000 R
b100000 M
#525
bx F
0E
1D
b0 !
b0 H
1"
0#
1-
#530
0-
b10000 2
b10 4
#535
bx !
bx H
0"
1#
1-
#540
b1000 C
0-
b11001 7
b110000000000101000 ,
b110000000000101000 :
b110000000000101000 R
b101000 M
#545
1-
#550
0-
b110 1
b100 3
#555
1-
#560
b10000 C
0-
b11010 7
b110000000000110000 ,
b110000000000110000 :
b110000000000110000 R
b110000 M
#565
1-
#570
0-
b111 1
b101 3
#575
1-
#580
b11000 C
0-
b11011 7
b110000000000111000 ,
b110000000000111000 :
b110000000000111000 R
b111000 M
#585
1-
#590
0-
b1000 1
b110 3
#595
1-
#600
b0 F
1E
0D
b0 C
b10 G
0-
b11100 7
b110000000001000000 ,
b110000000001000000 :
b110000000001000000 R
b1000000 M
#605
bx F
0E
1D
b0 !
b0 H
1"
0#
1-
#610
0-
b10001 2
b11 4
#615
bx !
bx H
0"
1#
1-
#620
b1000 C
0-
b11101 7
b110000000001001000 ,
b110000000001001000 :
b110000000001001000 R
b1001000 M
#625
1-
#630
0-
b1001 1
b111 3
#635
1-
#640
b10000 C
0-
b11110 7
b110000000001010000 ,
b110000000001010000 :
b110000000001010000 R
b1010000 M
#645
1-
#650
0-
b1010 1
b1000 3
#655
1-
#660
b11000 C
0-
b11111 7
b110000000001011000 ,
b110000000001011000 :
b110000000001011000 R
b1011000 M
#665
1-
#670
0-
b1011 1
b1001 3
#675
1-
#680
b0 F
1E
0D
b0 C
b11 G
0-
b100000 7
b110000000001100000 ,
b110000000001100000 :
b110000000001100000 R
b1100000 M
#685
bx F
0E
1D
b0 !
b0 H
1"
0#
1-
#690
0-
b10010 2
b100 4
#695
bx !
bx H
0"
1#
1-
#700
b1000 C
0-
b100001 7
b110000000001101000 ,
b110000000001101000 :
b110000000001101000 R
b1101000 M
#705
1-
#710
0-
b1100 1
b1010 3
#715
1-
#720
b10000 C
0-
b100010 7
b110000000001110000 ,
b110000000001110000 :
b110000000001110000 R
b1110000 M
#725
1-
#730
0-
b1101 1
b1011 3
#735
1-
#740
b11000 C
0-
b100011 7
b110000000001111000 ,
b110000000001111000 :
b110000000001111000 R
b1111000 M
#745
1-
#750
0-
b1110 1
b1100 3
#755
1-
#760
b0 F
1E
0D
b0 C
b0 G
b100000000000 I
0-
b100100 7
10
b11101110 /
b11101110 ;
b1000000000000000000 ,
b1000000000000000000 :
b11101110 S
b1000000000000000000 T
b0 4
b0 3
b10000000 M
#765
0E
1D
b0 !
b0 H
1"
0#
1-
#770
0-
b100 9
b1 6
#775
0"
1#
1-
#780
1E
0D
b1 G
0-
b100101 7
b1000000000000100000 ,
b1000000000000100000 :
b1000000000000100000 T
b100000 N
#785
0E
1D
1"
0#
1-
#790
0-
b101 9
b10 6
#795
0"
1#
1-
#800
1E
0D
b10 G
0-
b100110 7
b1000000000001000000 ,
b1000000000001000000 :
b1000000000001000000 T
b1000000 N
#805
0E
1D
1"
0#
1-
#810
0-
b110 9
b11 6
#815
0"
1#
1-
#820
1E
0D
b11 G
0-
b100111 7
b1000000000001100000 ,
b1000000000001100000 :
b1000000000001100000 T
b1100000 N
#825
0E
1D
1"
0#
1-
#830
0-
b111 9
b100 6
#835
0"
1#
1-
#840
b11101110 F
b0 G
0-
b101000 7
00
b1000000000000000000 ,
b1000000000000000000 :
b1000000000000000000 R
b0 6
b10000000 N
#845
b11101110 !
b11101110 H
1-
#850
0-
b1111 1
b1 3
#855
1-
#860
b1 G
0-
b101001 7
b1000000000000100000 ,
b1000000000000100000 :
b1000000000000100000 R
b100000 O
#865
1-
#870
0-
b10000 1
b10 3
#875
1-
#880
b10 G
0-
b101010 7
b1000000000001000000 ,
b1000000000001000000 :
b1000000000001000000 R
b1000000 O
#885
1-
#890
0-
b10001 1
b11 3
#895
1-
#900
b11 G
0-
b101011 7
b1000000000001100000 ,
b1000000000001100000 :
b1000000000001100000 R
b1100000 O
#905
1-
#910
0-
b10010 1
b100 3
#915
1-
#920
b0 F
1E
0D
b0 G
b101000000000 I
0-
b101100 7
10
b11110000 /
b11110000 ;
b1010000000000000000 ,
b1010000000000000000 :
b11110000 S
b1010000000000000000 T
b0 3
b10000000 O
#925
0E
1D
b0 !
b0 H
1"
0#
1-
#930
0-
b1000 9
b1 6
#935
0"
1#
1-
#940
b1 C
0-
b101101 7
b11110001 /
b11110001 ;
b1010000000000000001 ,
b1010000000000000001 :
b11110001 S
b1010000000000000001 T
b1 P
#945
1-
#950
0-
b1 8
b1 5
#955
1-
#960
b10 C
0-
b101110 7
b11110010 /
b11110010 ;
b1010000000000000010 ,
b1010000000000000010 :
b11110010 S
b1010000000000000010 T
b10 P
#965
1-
#970
0-
b10 8
b10 5
#975
1-
#980
b11 C
0-
b101111 7
b11110011 /
b11110011 ;
b1010000000000000011 ,
b1010000000000000011 :
b11110011 S
b1010000000000000011 T
b11 P
#985
1-
#990
0-
b11 8
b11 5
#995
1-
#1000
b100 C
0-
b110000 7
b11110100 /
b11110100 ;
b1010000000000000100 ,
b1010000000000000100 :
b11110100 S
b1010000000000000100 T
b100 P
#1005
1-
#1010
0-
b100 8
b100 5
#1015
1-
#1020
b101 C
0-
b110001 7
b11110101 /
b11110101 ;
b1010000000000000101 ,
b1010000000000000101 :
b11110101 S
b1010000000000000101 T
b101 P
#1025
1-
#1030
0-
b101 8
b101 5
#1035
1-
#1040
b110 C
0-
b110010 7
b11110110 /
b11110110 ;
b1010000000000000110 ,
b1010000000000000110 :
b11110110 S
b1010000000000000110 T
b110 P
#1045
1-
#1050
0-
b110 8
b110 5
#1055
1-
#1060
b111 C
0-
b110011 7
b11110111 /
b11110111 ;
b1010000000000000111 ,
b1010000000000000111 :
b11110111 S
b1010000000000000111 T
b111 P
#1065
1-
#1070
0-
b111 8
b111 5
#1075
1-
#1080
b1000 C
0-
b110100 7
b11111000 /
b11111000 ;
b1010000000000001000 ,
b1010000000000001000 :
b11111000 S
b1010000000000001000 T
b1000 P
#1085
1-
#1090
0-
b1000 8
b1000 5
#1095
1-
#1100
b1001 C
0-
b110101 7
b11111001 /
b11111001 ;
b1010000000000001001 ,
b1010000000000001001 :
b11111001 S
b1010000000000001001 T
b1001 P
#1105
1-
#1110
0-
b1001 8
b1001 5
#1115
1-
#1120
b1010 C
0-
b110110 7
b11111010 /
b11111010 ;
b1010000000000001010 ,
b1010000000000001010 :
b11111010 S
b1010000000000001010 T
b1010 P
#1125
1-
#1130
0-
b1010 8
b1010 5
#1135
1-
#1140
b1011 C
0-
b110111 7
b11111011 /
b11111011 ;
b1010000000000001011 ,
b1010000000000001011 :
b11111011 S
b1010000000000001011 T
b1011 P
#1145
1-
#1150
0-
b1011 8
b1011 5
#1155
1-
#1160
b1100 C
0-
b111000 7
b11111100 /
b11111100 ;
b1010000000000001100 ,
b1010000000000001100 :
b11111100 S
b1010000000000001100 T
b1100 P
#1165
1-
#1170
0-
b1100 8
b1100 5
#1175
1-
#1180
b1101 C
0-
b111001 7
b11111101 /
b11111101 ;
b1010000000000001101 ,
b1010000000000001101 :
b11111101 S
b1010000000000001101 T
b1101 P
#1185
1-
#1190
0-
b1101 8
b1101 5
#1195
1-
#1200
b1110 C
0-
b111010 7
b11111110 /
b11111110 ;
b1010000000000001110 ,
b1010000000000001110 :
b11111110 S
b1010000000000001110 T
b1110 P
#1205
1-
#1210
0-
b1110 8
b1110 5
#1215
1-
#1220
b1111 C
0-
b111011 7
b11111111 /
b11111111 ;
b1010000000000001111 ,
b1010000000000001111 :
b11111111 S
b1010000000000001111 T
b1111 P
#1225
1-
#1230
0-
b1111 8
b1111 5
#1235
1-
#1240
b10000 C
0-
b111100 7
b0 /
b0 ;
b1010000000000010000 ,
b1010000000000010000 :
b0 S
b1010000000000010000 T
b10000 P
#1245
1-
#1250
0-
b10000 8
b10000 5
#1255
1-
#1260
b10001 C
0-
b111101 7
b1 /
b1 ;
b1010000000000010001 ,
b1010000000000010001 :
b1 S
b1010000000000010001 T
b10001 P
#1265
1-
#1270
0-
b10001 8
b10001 5
#1275
1-
#1280
b10010 C
0-
b111110 7
b10 /
b10 ;
b1010000000000010010 ,
b1010000000000010010 :
b10 S
b1010000000000010010 T
b10010 P
#1285
1-
#1290
0-
b10010 8
b10010 5
#1295
1-
#1300
b10011 C
0-
b111111 7
b11 /
b11 ;
b1010000000000010011 ,
b1010000000000010011 :
b11 S
b1010000000000010011 T
b10011 P
#1305
1-
#1310
0-
b10011 8
b10011 5
#1315
1-
#1320
b10100 C
0-
b1000000 7
b100 /
b100 ;
b1010000000000010100 ,
b1010000000000010100 :
b100 S
b1010000000000010100 T
b10100 P
#1325
1-
#1330
0-
b10100 8
b10100 5
#1335
1-
#1340
b10101 C
0-
b1000001 7
b101 /
b101 ;
b1010000000000010101 ,
b1010000000000010101 :
b101 S
b1010000000000010101 T
b10101 P
#1345
1-
#1350
0-
b10101 8
b10101 5
#1355
1-
#1360
b10110 C
0-
b1000010 7
b110 /
b110 ;
b1010000000000010110 ,
b1010000000000010110 :
b110 S
b1010000000000010110 T
b10110 P
#1365
1-
#1370
0-
b10110 8
b10110 5
#1375
1-
#1380
b10111 C
0-
b1000011 7
b111 /
b111 ;
b1010000000000010111 ,
b1010000000000010111 :
b111 S
b1010000000000010111 T
b10111 P
#1385
1-
#1390
0-
b10111 8
b10111 5
#1395
1-
#1400
b11000 C
0-
b1000100 7
b1000 /
b1000 ;
b1010000000000011000 ,
b1010000000000011000 :
b1000 S
b1010000000000011000 T
b11000 P
#1405
1-
#1410
0-
b11000 8
b11000 5
#1415
1-
#1420
b11001 C
0-
b1000101 7
b1001 /
b1001 ;
b1010000000000011001 ,
b1010000000000011001 :
b1001 S
b1010000000000011001 T
b11001 P
#1425
1-
#1430
0-
b11001 8
b11001 5
#1435
1-
#1440
b11010 C
0-
b1000110 7
b1010 /
b1010 ;
b1010000000000011010 ,
b1010000000000011010 :
b1010 S
b1010000000000011010 T
b11010 P
#1445
1-
#1450
0-
b11010 8
b11010 5
#1455
1-
#1460
b11011 C
0-
b1000111 7
b1011 /
b1011 ;
b1010000000000011011 ,
b1010000000000011011 :
b1011 S
b1010000000000011011 T
b11011 P
#1465
1-
#1470
0-
b11011 8
b11011 5
#1475
1-
#1480
b11100 C
0-
b1001000 7
b1100 /
b1100 ;
b1010000000000011100 ,
b1010000000000011100 :
b1100 S
b1010000000000011100 T
b11100 P
#1485
1-
#1490
0-
b11100 8
b11100 5
#1495
1-
#1500
b11101 C
0-
b1001001 7
b1101 /
b1101 ;
b1010000000000011101 ,
b1010000000000011101 :
b1101 S
b1010000000000011101 T
b11101 P
#1505
1-
#1510
0-
b11101 8
b11101 5
#1515
1-
#1520
b11110 C
0-
b1001010 7
b1110 /
b1110 ;
b1010000000000011110 ,
b1010000000000011110 :
b1110 S
b1010000000000011110 T
b11110 P
#1525
1-
#1530
0-
b11110 8
b11110 5
#1535
1-
#1540
b11111 C
0-
b1001011 7
b1111 /
b1111 ;
b1010000000000011111 ,
b1010000000000011111 :
b1111 S
b1010000000000011111 T
b11111 P
#1545
1-
#1550
0-
b11111 8
b11111 5
#1555
1-
#1560
b11110000 F
b0 C
0-
b1001100 7
00
b1010000000000000000 ,
b1010000000000000000 :
b1010000000000000000 R
b100000 P
#1565
b11110000 !
b11110000 H
1-
#1570
0-
b10011 1
b1 3
#1575
1-
#1580
b11110001 F
b1 C
0-
b1001101 7
b1010000000000000001 ,
b1010000000000000001 :
b1010000000000000001 R
b1 Q
#1585
b11110001 !
b11110001 H
1-
#1590
0-
b10100 1
b10 3
#1595
1-
#1600
b11110010 F
b10 C
0-
b1001110 7
b1010000000000000010 ,
b1010000000000000010 :
b1010000000000000010 R
b10 Q
#1605
b11110010 !
b11110010 H
1-
#1610
0-
b10101 1
b11 3
#1615
1-
